Workbook

Sheet Dashboard
B2: DASHBOARD DE GESTÃO DE PROJETO · KYBERNUS CLI
B3: =CONCATENATE("GP: ",'Parâmetros'!$C$6," | Data de Status: ",TEXT('Parâmetros'!$C$10,"DD/MM/YYYY")," | Avanço real ",TEXT('Parâmetros'!$C$21,"0%")," vs planejado ",TEXT('Parâmetros'!$C$22,"0%")) -> GP: Guilherme Marafon | Data de Status: 31/05/2026 | Avanço real 43% vs planejado 64%
B5: VISÃO GERAL
B7: STATUS GERAL | E7: % DE CONCLUSÃO | H7: PRAZO · SPI | K7: CUSTO · CPI | N7: ORÇAMENTO CONSUMIDO
B8: =IF(AND(Dados!$B$40>=0.95,Dados!$B$42>=0.95),"🟢 NO PRAZO",IF(OR(Dados!$B$40<0.85,Dados!$B$42<0.85),"🔴 CRÍTICO","🟡 ATENÇÃO")) -> 🔴 CRÍTICO | E8: ='Parâmetros'!$C$21 -> 0.43177756 | H8: =Dados!$B$40 -> 0.67053612 | K8: =Dados!$B$42 -> 1.3651284 | N8: =Dados!$B$46 -> 0.3162908
B10: ="Prazo + Custo (EVM)" -> Prazo + Custo (EVM) | E10: =CONCATENATE("Planejado: ",TEXT('Parâmetros'!$C$22,"0%")) -> Planejado: 64% | H10: =IF(Dados!$B$40>=0.95,"No ritmo","Atrasado") -> Atrasado | K10: =IF(Dados!$B$42>=1,"Dentro do custo","Acima do custo") -> Dentro do custo | N10: =CONCATENATE("de ",TEXT('Parâmetros'!$C$13,"R$ #,##0")) -> de R$ 35.695
B12: ⏱ INDICADORES DE PRAZO E CUSTO (EVM)
B13: Indicador | E13: Valor | F13: Faixa OK | G13: ● | H13: Interpretação | K13: 📌 SITUAÇÃO DAS ATIVIDADES
B14: SPI — Prazo | E14: =Dados!$B$40 -> 0.67053612 | F14: ≥ 0,95 | G14: ● | H14: =IF(Dados!$B$40>=0.95,"Cronograma no ritmo","Atraso vs plano") -> Atraso vs plano | K14: =COUNTIF(Cronograma!$J$4:$J$97,"*Concluída*") -> 43 | M14: =COUNTIF(Cronograma!$J$4:$J$97,"*Em execução*") -> 1 | O14: =Dados!$B$41 -> 15412.3
B15: CPI — Custo | E15: =Dados!$B$42 -> 1.3651284 | F15: ≥ 0,95 | G15: ● | H15: =IF(Dados!$B$42>=1,"Eficiência de custo","Custo acima do previsto") -> Eficiência de custo | K15: Concluídas | M15: Em Execução | O15: EV — Valor Agregado
B16: CV — Variação Custo (R$) | E16: =Dados!$B$44 -> 4122.2999 | F16: ≥ 0 | G16: ● | H16: =IF(Dados!$B$44>=0,"Dentro do orçamento","Estouro de custo") -> Dentro do orçamento | K16: =COUNTIF(Cronograma!$J$4:$J$97,"*Atrasada*") -> 9 | M16: =COUNTIF(Cronograma!$J$4:$J$97,"*Não iniciada*") -> 37 | O16: =Dados!$B$43 -> 22985.04
B17: SV — Variação Prazo (R$) | E17: =Dados!$B$45 -> -7572.7405 | F17: ≥ 0 | G17: ● | H17: =IF(Dados!$B$45>=0,"Adiantado","Valor agregado abaixo do planejado") -> Valor agregado abaixo do planejado | K17: Atrasadas | M17: Não Iniciadas | O17: PV — Valor Planejado
B19: 📈 INDICADORES VISUAIS
B52: 🎯 PRÓXIMOS MARCOS | J52: ⚠ TOP 5 RISCOS (dinâmico — vem da aba Riscos)
B53: Marco | E53: Data | G53: Situação | J53: Risco | O53: Sev. | P53: Nível
B54: =Marcos!C5 -> Gerenciamento do Projeto | E54: =TEXT(Marcos!D5,"DD/MM/YYYY") -> 11/03/2026 | G54: =Marcos!E5 -> Concluído | J54: =CONCATENATE("R",TEXT(Dados!B50,"00")," · ",Dados!C50) -> R07 · Saída de um integrante da equipe durante o projeto | O54: =Dados!D50 -> 20 | P54: =Dados!E50 -> 🔴 Alto
B55: =Marcos!C6 -> Definição e Design | E55: =TEXT(Marcos!D6,"DD/MM/YYYY") -> 01/04/2026 | G55: =Marcos!E6 -> Concluído | J55: =CONCATENATE("R",TEXT(Dados!B51,"00")," · ",Dados!C51) -> R22 · Atraso no prazo final 01/07 devido à defasagem e redistribuição (MUD-01) | O55: =Dados!D51 -> 16 | P55: =Dados!E51 -> 🔴 Alto
B56: =Marcos!C7 -> Implementação das Funcionalidades | E56: =TEXT(Marcos!D7,"DD/MM/YYYY") -> 03/06/2026 | G56: =Marcos!E7 -> Previsto | J56: =CONCATENATE("R",TEXT(Dados!B52,"00")," · ",Dados!C52) -> R02 · Mudanças no escopo não controladas | O56: =Dados!D52 -> 12 | P56: =Dados!E52 -> 🟡 Médio
B57: =Marcos!C8 -> Testes e Documentação | E57: =TEXT(Marcos!D8,"DD/MM/YYYY") -> 17/06/2026 | G57: =Marcos!E8 -> Previsto | J57: =CONCATENATE("R",TEXT(Dados!B53,"00")," · ",Dados!C53) -> R06 · Disponibilidade limitada da equipe impactando o cronograma | O57: =Dados!D53 -> 12 | P57: =Dados!E53 -> 🟡 Médio
B58: =Marcos!C9 -> Divulgação e Encerramento | E58: =TEXT(Marcos!D9,"DD/MM/YYYY") -> 01/07/2026 | G58: =Marcos!E9 -> Previsto | J58: =CONCATENATE("R",TEXT(Dados!B54,"00")," · ",Dados!C54) -> R12 · Mudanças estruturais em frameworks suportados quebrando os templates gerados | O58: =Dados!D54 -> 12 | P58: =Dados!E54 -> 🟡 Médio
B60: 🛑 PROBLEMAS / IMPEDIMENTOS ATUAIS
B61: Descrição | J61: Impacto | N61: Severidade | P61: Responsável
B62: MUD-01 · Saída de desenvolvedor (Dev #3) durante a execução | J62: Perda de capacidade; ~137h redistribuídas a Dev #1/#2 (margem ~130h) | N62: Alta | P62: GP
B63: Atraso de cronograma: avanço real 40% vs 62% planejado (~22 p.p.) | J63: Prazo 01/07/2026 mantido condicionalmente — replanning imediato | N63: Alta | P63: GP
B64: MUD-02 · Novo perfil de acesso, permissões e segurança (+39h) | J64: Escopo ampliado na Fase 3 (Dev #2); +R$ 975 no custo | N64: Média | P64: GP / Dev #2
B65: Sobrecarga dos devs remanescentes e cobertura de testes | J65: Risco de erros/retrabalho; reforço de pair review | N65: Média | P65: GP / Devs

Sheet Cronograma
A1: 📅 CRONOGRAMA — KYBERNUS CLI (edite Horas, Responsável e % Real → tudo recalcula) | T1: Custo Real
A2: ID | B2: EAP | C2: Tarefa | D2: Início | E2: Término | F2: Dur | G2: Horas | H2: Responsável | I2: % Real | J2: Situação | K2: EV (h) | L2: PV (h) | M2: GP | N2: PM | O2: Dev #1 | P2: Dev #2 | Q2: Dev #3 | R2: MKT | S2: Custo (R$) | T2: Custo Real (R$)
A3: FASE 1 · Gerenciamento do Projeto
A4: 4 | B4: 1.1 | C4: Elaborar o Termo de Abertura do Projeto (TAP) | D4: 46085 | E4: 46087 | F4: 4 | G4: 8 | H4: GP | I4: 1 | J4: =IF(I4>=1,"✅ Concluída",IF(I4>0,"🔵 Em execução",IF(E4<'Parâmetros'!$C$10,"🔴 Atrasada","⚪ Não iniciada"))) -> ✅ Concluída | K4: =G4*I4 -> 8 | L4: =IF(E4=D4,IF('Parâmetros'!$C$10>=E4,G4,0),G4*MEDIAN(0,1,('Parâmetros'!$C$10-D4)/(E4-D4))) -> 8 | M4: =IF(ISNUMBER(SEARCH("GP",H4)),G4/(LEN(H4)-LEN(SUBSTITUTE(H4,"+",""))+1),0) -> 8 | N4: =IF(ISNUMBER(SEARCH("PM",H4)),G4/(LEN(H4)-LEN(SUBSTITUTE(H4,"+",""))+1),0) -> 0 | O4: =IF(ISNUMBER(SEARCH("Dev #1",H4)),G4/(LEN(H4)-LEN(SUBSTITUTE(H4,"+",""))+1),0) -> 0 | P4: =IF(ISNUMBER(SEARCH("Dev #2",H4)),G4/(LEN(H4)-LEN(SUBSTITUTE(H4,"+",""))+1),0) -> 0 | Q4: =IF(ISNUMBER(SEARCH("Dev #3",H4)),G4/(LEN(H4)-LEN(SUBSTITUTE(H4,"+",""))+1),0) -> 0 | R4: =IF(ISNUMBER(SEARCH("MKT",H4)),G4/(LEN(H4)-LEN(SUBSTITUTE(H4,"+",""))+1),0) -> 0 | S4: =(M4+N4)*'Parâmetros'!$C$15+(O4+P4+Q4+R4)*'Parâmetros'!$C$16 -> 240 | T4: =S4*I4 -> 240
A5: 5 | B5: 1.1 | C5: Apresentar e obter aprovação da patrocinadora | D5: 46090 | E5: 46090 | F5: 2 | G5: 4 | H5: GP | I5: 1 | J5: =IF(I5>=1,"✅ Concluída",IF(I5>0,"🔵 Em execução",IF(E5<'Parâmetros'!$C$10,"🔴 Atrasada","⚪ Não iniciada"))) -> ✅ Concluída | K5: =G5*I5 -> 4 | L5: =IF(E5=D5,IF('Parâmetros'!$C$10>=E5,G5,0),G5*MEDIAN(0,1,('Parâmetros'!$C$10-D5)/(E5-D5))) -> 4 | M5: =IF(ISNUMBER(SEARCH("GP",H5)),G5/(LEN(H5)-LEN(SUBSTITUTE(H5,"+",""))+1),0) -> 4 | N5: =IF(ISNUMBER(SEARCH("PM",H5)),G5/(LEN(H5)-LEN(SUBSTITUTE(H5,"+",""))+1),0) -> 0 | O5: =IF(ISNUMBER(SEARCH("Dev #1",H5)),G5/(LEN(H5)-LEN(SUBSTITUTE(H5,"+",""))+1),0) -> 0 | P5: =IF(ISNUMBER(SEARCH("Dev #2",H5)),G5/(LEN(H5)-LEN(SUBSTITUTE(H5,"+",""))+1),0) -> 0 | Q5: =IF(ISNUMBER(SEARCH("Dev #3",H5)),G5/(LEN(H5)-LEN(SUBSTITUTE(H5,"+",""))+1),0) -> 0 | R5: =IF(ISNUMBER(SEARCH("MKT",H5)),G5/(LEN(H5)-LEN(SUBSTITUTE(H5,"+",""))+1),0) -> 0 | S5: =(M5+N5)*'Parâmetros'!$C$15+(O5+P5+Q5+R5)*'Parâmetros'!$C$16 -> 120 | T5: =S5*I5 -> 120
A6: 6 | B6: 1.1 | C6: Designar formalmente o gerente do projeto | D6: 46090 | E6: 46090 | F6: 1 | G6: 2 | H6: PAT | I6: 1 | J6: =IF(I6>=1,"✅ Concluída",IF(I6>0,"🔵 Em execução",IF(E6<'Parâmetros'!$C$10,"🔴 Atrasada","⚪ Não iniciada"))) -> ✅ Concluída | K6: =G6*I6 -> 2 | L6: =IF(E6=D6,IF('Parâmetros'!$C$10>=E6,G6,0),G6*MEDIAN(0,1,('Parâmetros'!$C$10-D6)/(E6-D6))) -> 2 | M6: =IF(ISNUMBER(SEARCH("GP",H6)),G6/(LEN(H6)-LEN(SUBSTITUTE(H6,"+",""))+1),0) -> 0 | N6: =IF(ISNUMBER(SEARCH("PM",H6)),G6/(LEN(H6)-LEN(SUBSTITUTE(H6,"+",""))+1),0) -> 0 | O6: =IF(ISNUMBER(SEARCH("Dev #1",H6)),G6/(LEN(H6)-LEN(SUBSTITUTE(H6,"+",""))+1),0) -> 0 | P6: =IF(ISNUMBER(SEARCH("Dev #2",H6)),G6/(LEN(H6)-LEN(SUBSTITUTE(H6,"+",""))+1),0) -> 0 | Q6: =IF(ISNUMBER(SEARCH("Dev #3",H6)),G6/(LEN(H6)-LEN(SUBSTITUTE(H6,"+",""))+1),0) -> 0 | R6: =IF(ISNUMBER(SEARCH("MKT",H6)),G6/(LEN(H6)-LEN(SUBSTITUTE(H6,"+",""))+1),0) -> 0 | S6: =(M6+N6)*'Parâmetros'!$C$15+(O6+P6+Q6+R6)*'Parâmetros'!$C$16 -> 0 | T6: =S6*I6 -> 0
A7: 8 | B7: 1.2 | C7: Construir a EAP (fases e subentregas) | D7: 46091 | E7: 46093 | F7: 4 | G7: 8 | H7: GP+PM | I7: 1 | J7: =IF(I7>=1,"✅ Concluída",IF(I7>0,"🔵 Em execução",IF(E7<'Parâmetros'!$C$10,"🔴 Atrasada","⚪ Não iniciada"))) -> ✅ Concluída | K7: =G7*I7 -> 8 | L7: =IF(E7=D7,IF('Parâmetros'!$C$10>=E7,G7,0),G7*MEDIAN(0,1,('Parâmetros'!$C$10-D7)/(E7-D7))) -> 8 | M7: =IF(ISNUMBER(SEARCH("GP",H7)),G7/(LEN(H7)-LEN(SUBSTITUTE(H7,"+",""))+1),0) -> 4 | N7: =IF(ISNUMBER(SEARCH("PM",H7)),G7/(LEN(H7)-LEN(SUBSTITUTE(H7,"+",""))+1),0) -> 4 | O7: =IF(ISNUMBER(SEARCH("Dev #1",H7)),G7/(LEN(H7)-LEN(SUBSTITUTE(H7,"+",""))+1),0) -> 0 | P7: =IF(ISNUMBER(SEARCH("Dev #2",H7)),G7/(LEN(H7)-LEN(SUBSTITUTE(H7,"+",""))+1),0) -> 0 | Q7: =IF(ISNUMBER(SEARCH("Dev #3",H7)),G7/(LEN(H7)-LEN(SUBSTITUTE(H7,"+",""))+1),0) -> 0 | R7: =IF(ISNUMBER(SEARCH("MKT",H7)),G7/(LEN(H7)-LEN(SUBSTITUTE(H7,"+",""))+1),0) -> 0 | S7: =(M7+N7)*'Parâmetros'!$C$15+(O7+P7+Q7+R7)*'Parâmetros'!$C$16 -> 240 | T7: =S7*I7 -> 240
A8: 9 | B8: 1.2 | C8: Elaborar o Dicionário da EAP | D8: 46094 | E8: 46094 | F8: 2 | G8: 4 | H8: GP | I8: 1 | J8: =IF(I8>=1,"✅ Concluída",IF(I8>0,"🔵 Em execução",IF(E8<'Parâmetros'!$C$10,"🔴 Atrasada","⚪ Não iniciada"))) -> ✅ Concluída | K8: =G8*I8 -> 4 | L8: =IF(E8=D8,IF('Parâmetros'!$C$10>=E8,G8,0),G8*MEDIAN(0,1,('Parâmetros'!$C$10-D8)/(E8-D8))) -> 4 | M8: =IF(ISNUMBER(SEARCH("GP",H8)),G8/(LEN(H8)-LEN(SUBSTITUTE(H8,"+",""))+1),0) -> 4 | N8: =IF(ISNUMBER(SEARCH("PM",H8)),G8/(LEN(H8)-LEN(SUBSTITUTE(H8,"+",""))+1),0) -> 0 | O8: =IF(ISNUMBER(SEARCH("Dev #1",H8)),G8/(LEN(H8)-LEN(SUBSTITUTE(H8,"+",""))+1),0) -> 0 | P8: =IF(ISNUMBER(SEARCH("Dev #2",H8)),G8/(LEN(H8)-LEN(SUBSTITUTE(H8,"+",""))+1),0) -> 0 | Q8: =IF(ISNUMBER(SEARCH("Dev #3",H8)),G8/(LEN(H8)-LEN(SUBSTITUTE(H8,"+",""))+1),0) -> 0 | R8: =IF(ISNUMBER(SEARCH("MKT",H8)),G8/(LEN(H8)-LEN(SUBSTITUTE(H8,"+",""))+1),0) -> 0 | S8: =(M8+N8)*'Parâmetros'!$C$15+(O8+P8+Q8+R8)*'Parâmetros'!$C$16 -> 120 | T8: =S8*I8 -> 120
A9: 10 | B9: 1.2 | C9: Definir e documentar processo de controle de mudanças | D9: 46097 | E9: 46097 | F9: 2 | G9: 4 | H9: GP | I9: 1 | J9: =IF(I9>=1,"✅ Concluída",IF(I9>0,"🔵 Em execução",IF(E9<'Parâmetros'!$C$10,"🔴 Atrasada","⚪ Não iniciada"))) -> ✅ Concluída | K9: =G9*I9 -> 4 | L9: =IF(E9=D9,IF('Parâmetros'!$C$10>=E9,G9,0),G9*MEDIAN(0,1,('Parâmetros'!$C$10-D9)/(E9-D9))) -> 4 | M9: =IF(ISNUMBER(SEARCH("GP",H9)),G9/(LEN(H9)-LEN(SUBSTITUTE(H9,"+",""))+1),0) -> 4 | N9: =IF(ISNUMBER(SEARCH("PM",H9)),G9/(LEN(H9)-LEN(SUBSTITUTE(H9,"+",""))+1),0) -> 0 | O9: =IF(ISNUMBER(SEARCH("Dev #1",H9)),G9/(LEN(H9)-LEN(SUBSTITUTE(H9,"+",""))+1),0) -> 0 | P9: =IF(ISNUMBER(SEARCH("Dev #2",H9)),G9/(LEN(H9)-LEN(SUBSTITUTE(H9,"+",""))+1),0) -> 0 | Q9: =IF(ISNUMBER(SEARCH("Dev #3",H9)),G9/(LEN(H9)-LEN(SUBSTITUTE(H9,"+",""))+1),0) -> 0 | R9: =IF(ISNUMBER(SEARCH("MKT",H9)),G9/(LEN(H9)-LEN(SUBSTITUTE(H9,"+",""))+1),0) -> 0 | S9: =(M9+N9)*'Parâmetros'!$C$15+(O9+P9+Q9+R9)*'Parâmetros'!$C$16 -> 120 | T9: =S9*I9 -> 120
A10: 12 | B10: 1.3 | C10: Identificar e classificar os stakeholders | D10: 46094 | E10: 46094 | F10: 2 | G10: 4 | H10: PM | I10: 1 | J10: =IF(I10>=1,"✅ Concluída",IF(I10>0,"🔵 Em execução",IF(E10<'Parâmetros'!$C$10,"🔴 Atrasada","⚪ Não iniciada"))) -> ✅ Concluída | K10: =G10*I10 -> 4 | L10: =IF(E10=D10,IF('Parâmetros'!$C$10>=E10,G10,0),G10*MEDIAN(0,1,('Parâmetros'!$C$10-D10)/(E10-D10))) -> 4 | M10: =IF(ISNUMBER(SEARCH("GP",H10)),G10/(LEN(H10)-LEN(SUBSTITUTE(H10,"+",""))+1),0) -> 0 | N10: =IF(ISNUMBER(SEARCH("PM",H10)),G10/(LEN(H10)-LEN(SUBSTITUTE(H10,"+",""))+1),0) -> 4 | O10: =IF(ISNUMBER(SEARCH("Dev #1",H10)),G10/(LEN(H10)-LEN(SUBSTITUTE(H10,"+",""))+1),0) -> 0 | P10: =IF(ISNUMBER(SEARCH("Dev #2",H10)),G10/(LEN(H10)-LEN(SUBSTITUTE(H10,"+",""))+1),0) -> 0 | Q10: =IF(ISNUMBER(SEARCH("Dev #3",H10)),G10/(LEN(H10)-LEN(SUBSTITUTE(H10,"+",""))+1),0) -> 0 | R10: =IF(ISNUMBER(SEARCH("MKT",H10)),G10/(LEN(H10)-LEN(SUBSTITUTE(H10,"+",""))+1),0) -> 0 | S10: =(M10+N10)*'Parâmetros'!$C$15+(O10+P10+Q10+R10)*'Parâmetros'!$C$16 -> 120 | T10: =S10*I10 -> 120
A11: 13 | B11: 1.3 | C11: Elaborar mapa e registro de stakeholders | D11: 46097 | E11: 46097 | F11: 2 | G11: 4 | H11: PM | I11: 1 | J11: =IF(I11>=1,"✅ Concluída",IF(I11>0,"🔵 Em execução",IF(E11<'Parâmetros'!$C$10,"🔴 Atrasada","⚪ Não iniciada"))) -> ✅ Concluída | K11: =G11*I11 -> 4 | L11: =IF(E11=D11,IF('Parâmetros'!$C$10>=E11,G11,0),G11*MEDIAN(0,1,('Parâmetros'!$C$10-D11)/(E11-D11))) -> 4 | M11: =IF(ISNUMBER(SEARCH("GP",H11)),G11/(LEN(H11)-LEN(SUBSTITUTE(H11,"+",""))+1),0) -> 0 | N11: =IF(ISNUMBER(SEARCH("PM",H11)),G11/(LEN(H11)-LEN(SUBSTITUTE(H11,"+",""))+1),0) -> 4 | O11: =IF(ISNUMBER(SEARCH("Dev #1",H11)),G11/(LEN(H11)-LEN(SUBSTITUTE(H11,"+",""))+1),0) -> 0 | P11: =IF(ISNUMBER(SEARCH("Dev #2",H11)),G11/(LEN(H11)-LEN(SUBSTITUTE(H11,"+",""))+1),0) -> 0 | Q11: =IF(ISNUMBER(SEARCH("Dev #3",H11)),G11/(LEN(H11)-LEN(SUBSTITUTE(H11,"+",""))+1),0) -> 0 | R11: =IF(ISNUMBER(SEARCH("MKT",H11)),G11/(LEN(H11)-LEN(SUBSTITUTE(H11,"+",""))+1),0) -> 0 | S11: =(M11+N11)*'Parâmetros'!$C$15+(O11+P11+Q11+R11)*'Parâmetros'!$C$16 -> 120 | T11: =S11*I11 -> 120
A12: 14 | B12: 1.3 | C12: Definir estratégia de engajamento e plano de comunicação | D12: 46098 | E12: 46098 | F12: 2 | G12: 4 | H12: GP | I12: 1 | J12: =IF(I12>=1,"✅ Concluída",IF(I12>0,"🔵 Em execução",IF(E12<'Parâmetros'!$C$10,"🔴 Atrasada","⚪ Não iniciada"))) -> ✅ Concluída | K12: =G12*I12 -> 4 | L12: =IF(E12=D12,IF('Parâmetros'!$C$10>=E12,G12,0),G12*MEDIAN(0,1,('Parâmetros'!$C$10-D12)/(E12-D12))) -> 4 | M12: =IF(ISNUMBER(SEARCH("GP",H12)),G12/(LEN(H12)-LEN(SUBSTITUTE(H12,"+",""))+1),0) -> 4 | N12: =IF(ISNUMBER(SEARCH("PM",H12)),G12/(LEN(H12)-LEN(SUBSTITUTE(H12,"+",""))+1),0) -> 0 | O12: =IF(ISNUMBER(SEARCH("Dev #1",H12)),G12/(LEN(H12)-LEN(SUBSTITUTE(H12,"+",""))+1),0) -> 0 | P12: =IF(ISNUMBER(SEARCH("Dev #2",H12)),G12/(LEN(H12)-LEN(SUBSTITUTE(H12,"+",""))+1),0) -> 0 | Q12: =IF(ISNUMBER(SEARCH("Dev #3",H12)),G12/(LEN(H12)-LEN(SUBSTITUTE(H12,"+",""))+1),0) -> 0 | R12: =IF(ISNUMBER(SEARCH("MKT",H12)),G12/(LEN(H12)-LEN(SUBSTITUTE(H12,"+",""))+1),0) -> 0 | S12: =(M12+N12)*'Parâmetros'!$C$15+(O12+P12+Q12+R12)*'Parâmetros'!$C$16 -> 120 | T12: =S12*I12 -> 120
A13: 16 | B13: 1.4 | C13: Identificar e descrever os riscos | D13: 46099 | E13: 46099 | F13: 2 | G13: 4 | H13: GP | I13: 1 | J13: =IF(I13>=1,"✅ Concluída",IF(I13>0,"🔵 Em execução",IF(E13<'Parâmetros'!$C$10,"🔴 Atrasada","⚪ Não iniciada"))) -> ✅ Concluída | K13: =G13*I13 -> 4 | L13: =IF(E13=D13,IF('Parâmetros'!$C$10>=E13,G13,0),G13*MEDIAN(0,1,('Parâmetros'!$C$10-D13)/(E13-D13))) -> 4 | M13: =IF(ISNUMBER(SEARCH("GP",H13)),G13/(LEN(H13)-LEN(SUBSTITUTE(H13,"+",""))+1),0) -> 4 | N13: =IF(ISNUMBER(SEARCH("PM",H13)),G13/(LEN(H13)-LEN(SUBSTITUTE(H13,"+",""))+1),0) -> 0 | O13: =IF(ISNUMBER(SEARCH("Dev #1",H13)),G13/(LEN(H13)-LEN(SUBSTITUTE(H13,"+",""))+1),0) -> 0 | P13: =IF(ISNUMBER(SEARCH("Dev #2",H13)),G13/(LEN(H13)-LEN(SUBSTITUTE(H13,"+",""))+1),0) -> 0 | Q13: =IF(ISNUMBER(SEARCH("Dev #3",H13)),G13/(LEN(H13)-LEN(SUBSTITUTE(H13,"+",""))+1),0) -> 0 | R13: =IF(ISNUMBER(SEARCH("MKT",H13)),G13/(LEN(H13)-LEN(SUBSTITUTE(H13,"+",""))+1),0) -> 0 | S13: =(M13+N13)*'Parâmetros'!$C$15+(O13+P13+Q13+R13)*'Parâmetros'!$C$16 -> 120 | T13: =S13*I13 -> 120
A14: 17 | B14: 1.4 | C14: Analisar probabilidade e impacto (matriz P×I) | D14: 46100 | E14: 46100 | F14: 2 | G14: 4 | H14: GP | I14: 1 | J14: =IF(I14>=1,"✅ Concluída",IF(I14>0,"🔵 Em execução",IF(E14<'Parâmetros'!$C$10,"🔴 Atrasada","⚪ Não iniciada"))) -> ✅ Concluída | K14: =G14*I14 -> 4 | L14: =IF(E14=D14,IF('Parâmetros'!$C$10>=E14,G14,0),G14*MEDIAN(0,1,('Parâmetros'!$C$10-D14)/(E14-D14))) -> 4 | M14: =IF(ISNUMBER(SEARCH("GP",H14)),G14/(LEN(H14)-LEN(SUBSTITUTE(H14,"+",""))+1),0) -> 4 | N14: =IF(ISNUMBER(SEARCH("PM",H14)),G14/(LEN(H14)-LEN(SUBSTITUTE(H14,"+",""))+1),0) -> 0 | O14: =IF(ISNUMBER(SEARCH("Dev #1",H14)),G14/(LEN(H14)-LEN(SUBSTITUTE(H14,"+",""))+1),0) -> 0 | P14: =IF(ISNUMBER(SEARCH("Dev #2",H14)),G14/(LEN(H14)-LEN(SUBSTITUTE(H14,"+",""))+1),0) -> 0 | Q14: =IF(ISNUMBER(SEARCH("Dev #3",H14)),G14/(LEN(H14)-LEN(SUBSTITUTE(H14,"+",""))+1),0) -> 0 | R14: =IF(ISNUMBER(SEARCH("MKT",H14)),G14/(LEN(H14)-LEN(SUBSTITUTE(H14,"+",""))+1),0) -> 0 | S14: =(M14+N14)*'Parâmetros'!$C$15+(O14+P14+Q14+R14)*'Parâmetros'!$C$16 -> 120 | T14: =S14*I14 -> 120
A15: 18 | B15: 1.4 | C15: Definir planos de resposta e contingência | D15: 46101 | E15: 46105 | F15: 4 | G15: 8 | H15: GP | I15: 1 | J15: =IF(I15>=1,"✅ Concluída",IF(I15>0,"🔵 Em execução",IF(E15<'Parâmetros'!$C$10,"🔴 Atrasada","⚪ Não iniciada"))) -> ✅ Concluída | K15: =G15*I15 -> 8 | L15: =IF(E15=D15,IF('Parâmetros'!$C$10>=E15,G15,0),G15*MEDIAN(0,1,('Parâmetros'!$C$10-D15)/(E15-D15))) -> 8 | M15: =IF(ISNUMBER(SEARCH("GP",H15)),G15/(LEN(H15)-LEN(SUBSTITUTE(H15,"+",""))+1),0) -> 8 | N15: =IF(ISNUMBER(SEARCH("PM",H15)),G15/(LEN(H15)-LEN(SUBSTITUTE(H15,"+",""))+1),0) -> 0 | O15: =IF(ISNUMBER(SEARCH("Dev #1",H15)),G15/(LEN(H15)-LEN(SUBSTITUTE(H15,"+",""))+1),0) -> 0 | P15: =IF(ISNUMBER(SEARCH("Dev #2",H15)),G15/(LEN(H15)-LEN(SUBSTITUTE(H15,"+",""))+1),0) -> 0 | Q15: =IF(ISNUMBER(SEARCH("Dev #3",H15)),G15/(LEN(H15)-LEN(SUBSTITUTE(H15,"+",""))+1),0) -> 0 | R15: =IF(ISNUMBER(SEARCH("MKT",H15)),G15/(LEN(H15)-LEN(SUBSTITUTE(H15,"+",""))+1),0) -> 0 | S15: =(M15+N15)*'Parâmetros'!$C$15+(O15+P15+Q15+R15)*'Parâmetros'!$C$16 -> 240 | T15: =S15*I15 -> 240
... A21: 26 | B21: 1.6 | C21: Obter aceite formal da patrocinadora | D21: 46204 | E21: 46204 | F21: 1 | G21: 2 | H21: PAT | I21: 0 | J21: =IF(I21>=1,"✅ Concluída",IF(I21>0,"🔵 Em execução",IF(E21<'Parâmetros'!$C$10,"🔴 Atrasada","⚪ Não iniciada"))) -> ⚪ Não iniciada | K21: =G21*I21 -> 0 | L21: =IF(E21=D21,IF('Parâmetros'!$C$10>=E21,G21,0),G21*MEDIAN(0,1,('Parâmetros'!$C$10-D21)/(E21-D21))) -> 0 | M21: =IF(ISNUMBER(SEARCH("GP",H21)),G21/(LEN(H21)-LEN(SUBSTITUTE(H21,"+",""))+1),0) -> 0 | N21: =IF(ISNUMBER(SEARCH("PM",H21)),G21/(LEN(H21)-LEN(SUBSTITUTE(H21,"+",""))+1),0) -> 0 | O21: =IF(ISNUMBER(SEARCH("Dev #1",H21)),G21/(LEN(H21)-LEN(SUBSTITUTE(H21,"+",""))+1),0) -> 0 | P21: =IF(ISNUMBER(SEARCH("Dev #2",H21)),G21/(LEN(H21)-LEN(SUBSTITUTE(H21,"+",""))+1),0) -> 0 | Q21: =IF(ISNUMBER(SEARCH("Dev #3",H21)),G21/(LEN(H21)-LEN(SUBSTITUTE(H21,"+",""))+1),0) -> 0 | R21: =IF(ISNUMBER(SEARCH("MKT",H21)),G21/(LEN(H21)-LEN(SUBSTITUTE(H21,"+",""))+1),0) -> 0 | S21: =(M21+N21)*'Parâmetros'!$C$15+(O21+P21+Q21+R21)*'Parâmetros'!$C$16 -> 0 | T21: =S21*I21 -> 0
A22: FASE 2 · Definição e Design
A23: 29 | B23: 2.1 | C23: Levantar e documentar RFs e RNFs com stakeholders | D23: 46106 | E23: 46112 | F23: 6 | G23: 12 | H23: PM+GP | I23: 1 | J23: =IF(I23>=1,"✅ Concluída",IF(I23>0,"🔵 Em execução",IF(E23<'Parâmetros'!$C$10,"🔴 Atrasada","⚪ Não iniciada"))) -> ✅ Concluída | K23: =G23*I23 -> 12 | L23: =IF(E23=D23,IF('Parâmetros'!$C$10>=E23,G23,0),G23*MEDIAN(0,1,('Parâmetros'!$C$10-D23)/(E23-D23))) -> 12 | M23: =IF(ISNUMBER(SEARCH("GP",H23)),G23/(LEN(H23)-LEN(SUBSTITUTE(H23,"+",""))+1),0) -> 6 | N23: =IF(ISNUMBER(SEARCH("PM",H23)),G23/(LEN(H23)-LEN(SUBSTITUTE(H23,"+",""))+1),0) -> 6 | O23: =IF(ISNUMBER(SEARCH("Dev #1",H23)),G23/(LEN(H23)-LEN(SUBSTITUTE(H23,"+",""))+1),0) -> 0 | P23: =IF(ISNUMBER(SEARCH("Dev #2",H23)),G23/(LEN(H23)-LEN(SUBSTITUTE(H23,"+",""))+1),0) -> 0 | Q23: =IF(ISNUMBER(SEARCH("Dev #3",H23)),G23/(LEN(H23)-LEN(SUBSTITUTE(H23,"+",""))+1),0) -> 0 | R23: =IF(ISNUMBER(SEARCH("MKT",H23)),G23/(LEN(H23)-LEN(SUBSTITUTE(H23,"+",""))+1),0) -> 0 | S23: =(M23+N23)*'Parâmetros'!$C$15+(O23+P23+Q23+R23)*'Parâmetros'!$C$16 -> 360 | T23: =S23*I23 -> 360
A24: 30 | B24: 2.1 | C24: Priorizar requisitos com PM (Alta/Média/Baixa) | D24: 46113 | E24: 46114 | F24: 3 | G24: 6 | H24: PM | I24: 1 | J24: =IF(I24>=1,"✅ Concluída",IF(I24>0,"🔵 Em execução",IF(E24<'Parâmetros'!$C$10,"🔴 Atrasada","⚪ Não iniciada"))) -> ✅ Concluída | K24: =G24*I24 -> 6 | L24: =IF(E24=D24,IF('Parâmetros'!$C$10>=E24,G24,0),G24*MEDIAN(0,1,('Parâmetros'!$C$10-D24)/(E24-D24))) -> 6 | M24: =IF(ISNUMBER(SEARCH("GP",H24)),G24/(LEN(H24)-LEN(SUBSTITUTE(H24,"+",""))+1),0) -> 0 | N24: =IF(ISNUMBER(SEARCH("PM",H24)),G24/(LEN(H24)-LEN(SUBSTITUTE(H24,"+",""))+1),0) -> 6 | O24: =IF(ISNUMBER(SEARCH("Dev #1",H24)),G24/(LEN(H24)-LEN(SUBSTITUTE(H24,"+",""))+1),0) -> 0 | P24: =IF(ISNUMBER(SEARCH("Dev #2",H24)),G24/(LEN(H24)-LEN(SUBSTITUTE(H24,"+",""))+1),0) -> 0 | Q24: =IF(ISNUMBER(SEARCH("Dev #3",H24)),G24/(LEN(H24)-LEN(SUBSTITUTE(H24,"+",""))+1),0) -> 0 | R24: =IF(ISNUMBER(SEARCH("MKT",H24)),G24/(LEN(H24)-LEN(SUBSTITUTE(H24,"+",""))+1),0) -> 0 | S24: =(M24+N24)*'Parâmetros'!$C$15+(O24+P24+Q24+R24)*'Parâmetros'!$C$16 -> 180 | T24: =S24*I24 -> 180
A25: 31 | B25: 2.1 | C25: Definir critérios de aceite por requisito | D25: 46115 | E25: 46118 | F25: 3 | G25: 6 | H25: PM+GP | I25: 1 | J25: =IF(I25>=1,"✅ Concluída",IF(I25>0,"🔵 Em execução",IF(E25<'Parâmetros'!$C$10,"🔴 Atrasada","⚪ Não iniciada"))) -> ✅ Concluída | K25: =G25*I25 -> 6 | L25: =IF(E25=D25,IF('Parâmetros'!$C$10>=E25,G25,0),G25*MEDIAN(0,1,('Parâmetros'!$C$10-D25)/(E25-D25))) -> 6 | M25: =IF(ISNUMBER(SEARCH("GP",H25)),G25/(LEN(H25)-LEN(SUBSTITUTE(H25,"+",""))+1),0) -> 3 | N25: =IF(ISNUMBER(SEARCH("PM",H25)),G25/(LEN(H25)-LEN(SUBSTITUTE(H25,"+",""))+1),0) -> 3 | O25: =IF(ISNUMBER(SEARCH("Dev #1",H25)),G25/(LEN(H25)-LEN(SUBSTITUTE(H25,"+",""))+1),0) -> 0 | P25: =IF(ISNUMBER(SEARCH("Dev #2",H25)),G25/(LEN(H25)-LEN(SUBSTITUTE(H25,"+",""))+1),0) -> 0 | Q25: =IF(ISNUMBER(SEARCH("Dev #3",H25)),G25/(LEN(H25)-LEN(SUBSTITUTE(H25,"+",""))+1),0) -> 0 | R25: =IF(ISNUMBER(SEARCH("MKT",H25)),G25/(LEN(H25)-LEN(SUBSTITUTE(H25,"+",""))+1),0) -> 0 | S25: =(M25+N25)*'Parâmetros'!$C$15+(O25+P25+Q25+R25)*'Parâmetros'!$C$16 -> 180 | T25: =S25*I25 -> 180
A26: 33 | B26: 2.2 | C26: Definir arquitetura dos 4 módulos do CLI | D26: 46119 | E26: 46119 | F26: 1 | G26: 8 | H26: Dev #1+Dev #2+Dev #3 | I26: 1 | J26: =IF(I26>=1,"✅ Concluída",IF(I26>0,"🔵 Em execução",IF(E26<'Parâmetros'!$C$10,"🔴 Atrasada","⚪ Não iniciada"))) -> ✅ Concluída | K26: =G26*I26 -> 8 | L26: =IF(E26=D26,IF('Parâmetros'!$C$10>=E26,G26,0),G26*MEDIAN(0,1,('Parâmetros'!$C$10-D26)/(E26-D26))) -> 8 | M26: =IF(ISNUMBER(SEARCH("GP",H26)),G26/(LEN(H26)-LEN(SUBSTITUTE(H26,"+",""))+1),0) -> 0 | N26: =IF(ISNUMBER(SEARCH("PM",H26)),G26/(LEN(H26)-LEN(SUBSTITUTE(H26,"+",""))+1),0) -> 0 | O26: =IF(ISNUMBER(SEARCH("Dev #1",H26)),G26/(LEN(H26)-LEN(SUBSTITUTE(H26,"+",""))+1),0) -> 2.6666667 | P26: =IF(ISNUMBER(SEARCH("Dev #2",H26)),G26/(LEN(H26)-LEN(SUBSTITUTE(H26,"+",""))+1),0) -> 2.6666667 | Q26: =IF(ISNUMBER(SEARCH("Dev #3",H26)),G26/(LEN(H26)-LEN(SUBSTITUTE(H26,"+",""))+1),0) -> 2.6666667 | R26: =IF(ISNUMBER(SEARCH("MKT",H26)),G26/(LEN(H26)-LEN(SUBSTITUTE(H26,"+",""))+1),0) -> 0 | S26: =(M26+N26)*'Parâmetros'!$C$15+(O26+P26+Q26+R26)*'Parâmetros'!$C$16 -> 200 | T26: =S26*I26 -> 200
A27: 34 | B27: 2.2 | C27: Especificar contratos de interface entre módulos | D27: 46120 | E27: 46120 | F27: 1 | G27: 8 | H27: Dev #1+Dev #2+Dev #3 | I27: 1 | J27: =IF(I27>=1,"✅ Concluída",IF(I27>0,"🔵 Em execução",IF(E27<'Parâmetros'!$C$10,"🔴 Atrasada","⚪ Não iniciada"))) -> ✅ Concluída | K27: =G27*I27 -> 8 | L27: =IF(E27=D27,IF('Parâmetros'!$C$10>=E27,G27,0),G27*MEDIAN(0,1,('Parâmetros'!$C$10-D27)/(E27-D27))) -> 8 | M27: =IF(ISNUMBER(SEARCH("GP",H27)),G27/(LEN(H27)-LEN(SUBSTITUTE(H27,"+",""))+1),0) -> 0 | N27: =IF(ISNUMBER(SEARCH("PM",H27)),G27/(LEN(H27)-LEN(SUBSTITUTE(H27,"+",""))+1),0) -> 0 | O27: =IF(ISNUMBER(SEARCH("Dev #1",H27)),G27/(LEN(H27)-LEN(SUBSTITUTE(H27,"+",""))+1),0) -> 2.6666667 | P27: =IF(ISNUMBER(SEARCH("Dev #2",H27)),G27/(LEN(H27)-LEN(SUBSTITUTE(H27,"+",""))+1),0) -> 2.6666667 | Q27: =IF(ISNUMBER(SEARCH("Dev #3",H27)),G27/(LEN(H27)-LEN(SUBSTITUTE(H27,"+",""))+1),0) -> 2.6666667 | R27: =IF(ISNUMBER(SEARCH("MKT",H27)),G27/(LEN(H27)-LEN(SUBSTITUTE(H27,"+",""))+1),0) -> 0 | S27: =(M27+N27)*'Parâmetros'!$C$15+(O27+P27+Q27+R27)*'Parâmetros'!$C$16 -> 200 | T27: =S27*I27 -> 200
A28: 35 | B28: 2.2 | C28: Validar e decidir serviços externos | D28: 46121 | E28: 46121 | F28: 1 | G28: 8 | H28: Dev #1+Dev #2+Dev #3+PM | I28: 1 | J28: =IF(I28>=1,"✅ Concluída",IF(I28>0,"🔵 Em execução",IF(E28<'Parâmetros'!$C$10,"🔴 Atrasada","⚪ Não iniciada"))) -> ✅ Concluída | K28: =G28*I28 -> 8 | L28: =IF(E28=D28,IF('Parâmetros'!$C$10>=E28,G28,0),G28*MEDIAN(0,1,('Parâmetros'!$C$10-D28)/(E28-D28))) -> 8 | M28: =IF(ISNUMBER(SEARCH("GP",H28)),G28/(LEN(H28)-LEN(SUBSTITUTE(H28,"+",""))+1),0) -> 0 | N28: =IF(ISNUMBER(SEARCH("PM",H28)),G28/(LEN(H28)-LEN(SUBSTITUTE(H28,"+",""))+1),0) -> 2 | O28: =IF(ISNUMBER(SEARCH("Dev #1",H28)),G28/(LEN(H28)-LEN(SUBSTITUTE(H28,"+",""))+1),0) -> 2 | P28: =IF(ISNUMBER(SEARCH("Dev #2",H28)),G28/(LEN(H28)-LEN(SUBSTITUTE(H28,"+",""))+1),0) -> 2 | Q28: =IF(ISNUMBER(SEARCH("Dev #3",H28)),G28/(LEN(H28)-LEN(SUBSTITUTE(H28,"+",""))+1),0) -> 2 | R28: =IF(ISNUMBER(SEARCH("MKT",H28)),G28/(LEN(H28)-LEN(SUBSTITUTE(H28,"+",""))+1),0) -> 0 | S28: =(M28+N28)*'Parâmetros'!$C$15+(O28+P28+Q28+R28)*'Parâmetros'!$C$16 -> 210 | T28: =S28*I28 -> 210
A29: 27 | B29: 2.2 | C29: Pesquisar e selecionar fornecedores dos serviços externos (Gemini, PostHog, Supabase, npm, Vercel) | D29: 46122 | E29: 46122 | F29: 1 | G29: 4 | H29: GP+PM | I29: 1 | J29: =IF(I29>=1,"✅ Concluída",IF(I29>0,"🔵 Em execução",IF(E29<'Parâmetros'!$C$10,"🔴 Atrasada","⚪ Não iniciada"))) -> ✅ Concluída | K29: =G29*I29 -> 4 | L29: =IF(E29=D29,IF('Parâmetros'!$C$10>=E29,G29,0),G29*MEDIAN(0,1,('Parâmetros'!$C$10-D29)/(E29-D29))) -> 4 | M29: =IF(ISNUMBER(SEARCH("GP",H29)),G29/(LEN(H29)-LEN(SUBSTITUTE(H29,"+",""))+1),0) -> 2 | N29: =IF(ISNUMBER(SEARCH("PM",H29)),G29/(LEN(H29)-LEN(SUBSTITUTE(H29,"+",""))+1),0) -> 2 | O29: =IF(ISNUMBER(SEARCH("Dev #1",H29)),G29/(LEN(H29)-LEN(SUBSTITUTE(H29,"+",""))+1),0) -> 0 | P29: =IF(ISNUMBER(SEARCH("Dev #2",H29)),G29/(LEN(H29)-LEN(SUBSTITUTE(H29,"+",""))+1),0) -> 0 | Q29: =IF(ISNUMBER(SEARCH("Dev #3",H29)),G29/(LEN(H29)-LEN(SUBSTITUTE(H29,"+",""))+1),0) -> 0 | R29: =IF(ISNUMBER(SEARCH("MKT",H29)),G29/(LEN(H29)-LEN(SUBSTITUTE(H29,"+",""))+1),0) -> 0 | S29: =(M29+N29)*'Parâmetros'!$C$15+(O29+P29+Q29+R29)*'Parâmetros'!$C$16 -> 120 | T29: =S29*I29 -> 120
A30: 28 | B30: 2.2 | C30: Avaliar planos gratuitos, limites técnicos e termos de uso (free tier) | D30: 46125 | E30: 46125 | F30: 1 | G30: 4 | H30: Dev #1 | I30: 1 | J30: =IF(I30>=1,"✅ Concluída",IF(I30>0,"🔵 Em execução",IF(E30<'Parâmetros'!$C$10,"🔴 Atrasada","⚪ Não iniciada"))) -> ✅ Concluída | K30: =G30*I30 -> 4 | L30: =IF(E30=D30,IF('Parâmetros'!$C$10>=E30,G30,0),G30*MEDIAN(0,1,('Parâmetros'!$C$10-D30)/(E30-D30))) -> 4 | M30: =IF(ISNUMBER(SEARCH("GP",H30)),G30/(LEN(H30)-LEN(SUBSTITUTE(H30,"+",""))+1),0) -> 0 | N30: =IF(ISNUMBER(SEARCH("PM",H30)),G30/(LEN(H30)-LEN(SUBSTITUTE(H30,"+",""))+1),0) -> 0 | O30: =IF(ISNUMBER(SEARCH("Dev #1",H30)),G30/(LEN(H30)-LEN(SUBSTITUTE(H30,"+",""))+1),0) -> 4 | P30: =IF(ISNUMBER(SEARCH("Dev #2",H30)),G30/(LEN(H30)-LEN(SUBSTITUTE(H30,"+",""))+1),0) -> 0 | Q30: =IF(ISNUMBER(SEARCH("Dev #3",H30)),G30/(LEN(H30)-LEN(SUBSTITUTE(H30,"+",""))+1),0) -> 0 | R30: =IF(ISNUMBER(SEARCH("MKT",H30)),G30/(LEN(H30)-LEN(SUBSTITUTE(H30,"+",""))+1),0) -> 0 | S30: =(M30+N30)*'Parâmetros'!$C$15+(O30+P30+Q30+R30)*'Parâmetros'!$C$16 -> 100 | T30: =S30*I30 -> 100
A31: 32 | B31: 2.2 | C31: Aprovar formalmente as aquisições com a patrocinadora (custo R$ 0 — planos gratuitos) | D31: 46126 | E31: 46126 | F31: 1 | G31: 2 | H31: GP | I31: 1 | J31: =IF(I31>=1,"✅ Concluída",IF(I31>0,"🔵 Em execução",IF(E31<'Parâmetros'!$C$10,"🔴 Atrasada","⚪ Não iniciada"))) -> ✅ Concluída | K31: =G31*I31 -> 2 | L31: =IF(E31=D31,IF('Parâmetros'!$C$10>=E31,G31,0),G31*MEDIAN(0,1,('Parâmetros'!$C$10-D31)/(E31-D31))) -> 2 | M31: =IF(ISNUMBER(SEARCH("GP",H31)),G31/(LEN(H31)-LEN(SUBSTITUTE(H31,"+",""))+1),0) -> 2 | N31: =IF(ISNUMBER(SEARCH("PM",H31)),G31/(LEN(H31)-LEN(SUBSTITUTE(H31,"+",""))+1),0) -> 0 | O31: =IF(ISNUMBER(SEARCH("Dev #1",H31)),G31/(LEN(H31)-LEN(SUBSTITUTE(H31,"+",""))+1),0) -> 0 | P31: =IF(ISNUMBER(SEARCH("Dev #2",H31)),G31/(LEN(H31)-LEN(SUBSTITUTE(H31,"+",""))+1),0) -> 0 | Q31: =IF(ISNUMBER(SEARCH("Dev #3",H31)),G31/(LEN(H31)-LEN(SUBSTITUTE(H31,"+",""))+1),0) -> 0 | R31: =IF(ISNUMBER(SEARCH("MKT",H31)),G31/(LEN(H31)-LEN(SUBSTITUTE(H31,"+",""))+1),0) -> 0 | S31: =(M31+N31)*'Parâmetros'!$C$15+(O31+P31+Q31+R31)*'Parâmetros'!$C$16 -> 60 | T31: =S31*I31 -> 60
A32: 36 | B32: 2.2 | C32: Provisionar contas e chaves de acesso (Google Gemini API, PostHog, Supabase) | D32: 46126 | E32: 46127 | F32: 2 | G32: 6 | H32: Dev #1 | I32: 1 | J32: =IF(I32>=1,"✅ Concluída",IF(I32>0,"🔵 Em execução",IF(E32<'Parâmetros'!$C$10,"🔴 Atrasada","⚪ Não iniciada"))) -> ✅ Concluída | K32: =G32*I32 -> 6 | L32: =IF(E32=D32,IF('Parâmetros'!$C$10>=E32,G32,0),G32*MEDIAN(0,1,('Parâmetros'!$C$10-D32)/(E32-D32))) -> 6 | M32: =IF(ISNUMBER(SEARCH("GP",H32)),G32/(LEN(H32)-LEN(SUBSTITUTE(H32,"+",""))+1),0) -> 0 | N32: =IF(ISNUMBER(SEARCH("PM",H32)),G32/(LEN(H32)-LEN(SUBSTITUTE(H32,"+",""))+1),0) -> 0 | O32: =IF(ISNUMBER(SEARCH("Dev #1",H32)),G32/(LEN(H32)-LEN(SUBSTITUTE(H32,"+",""))+1),0) -> 6 | P32: =IF(ISNUMBER(SEARCH("Dev #2",H32)),G32/(LEN(H32)-LEN(SUBSTITUTE(H32,"+",""))+1),0) -> 0 | Q32: =IF(ISNUMBER(SEARCH("Dev #3",H32)),G32/(LEN(H32)-LEN(SUBSTITUTE(H32,"+",""))+1),0) -> 0 | R32: =IF(ISNUMBER(SEARCH("MKT",H32)),G32/(LEN(H32)-LEN(SUBSTITUTE(H32,"+",""))+1),0) -> 0 | S32: =(M32+N32)*'Parâmetros'!$C$15+(O32+P32+Q32+R32)*'Parâmetros'!$C$16 -> 150 | T32: =S32*I32 -> 150
A33: 40 | B33: 2.2 | C33: Registrar conta/organização no npm e provisionar deploy na Vercel/Netlify | D33: 46127 | E33: 46128 | F33: 2 | G33: 4 | H33: Dev #2 | I33: 1 | J33: =IF(I33>=1,"✅ Concluída",IF(I33>0,"🔵 Em execução",IF(E33<'Parâmetros'!$C$10,"🔴 Atrasada","⚪ Não iniciada"))) -> ✅ Concluída | K33: =G33*I33 -> 4 | L33: =IF(E33=D33,IF('Parâmetros'!$C$10>=E33,G33,0),G33*MEDIAN(0,1,('Parâmetros'!$C$10-D33)/(E33-D33))) -> 4 | M33: =IF(ISNUMBER(SEARCH("GP",H33)),G33/(LEN(H33)-LEN(SUBSTITUTE(H33,"+",""))+1),0) -> 0 | N33: =IF(ISNUMBER(SEARCH("PM",H33)),G33/(LEN(H33)-LEN(SUBSTITUTE(H33,"+",""))+1),0) -> 0 | O33: =IF(ISNUMBER(SEARCH("Dev #1",H33)),G33/(LEN(H33)-LEN(SUBSTITUTE(H33,"+",""))+1),0) -> 0 | P33: =IF(ISNUMBER(SEARCH("Dev #2",H33)),G33/(LEN(H33)-LEN(SUBSTITUTE(H33,"+",""))+1),0) -> 4 | Q33: =IF(ISNUMBER(SEARCH("Dev #3",H33)),G33/(LEN(H33)-LEN(SUBSTITUTE(H33,"+",""))+1),0) -> 0 | R33: =IF(ISNUMBER(SEARCH("MKT",H33)),G33/(LEN(H33)-LEN(SUBSTITUTE(H33,"+",""))+1),0) -> 0 | S33: =(M33+N33)*'Parâmetros'!$C$15+(O33+P33+Q33+R33)*'Parâmetros'!$C$16 -> 100 | T33: =S33*I33 -> 100
A34: 44 | B34: 2.2 | C34: Validar disponibilidade e limites dos serviços adquiridos (atende à necessidade do projeto) | D34: 46128 | E34: 46128 | F34: 1 | G34: 4 | H34: Dev #1 | I34: 1 | J34: =IF(I34>=1,"✅ Concluída",IF(I34>0,"🔵 Em execução",IF(E34<'Parâmetros'!$C$10,"🔴 Atrasada","⚪ Não iniciada"))) -> ✅ Concluída | K34: =G34*I34 -> 4 | L34: =IF(E34=D34,IF('Parâmetros'!$C$10>=E34,G34,0),G34*MEDIAN(0,1,('Parâmetros'!$C$10-D34)/(E34-D34))) -> 4 | M34: =IF(ISNUMBER(SEARCH("GP",H34)),G34/(LEN(H34)-LEN(SUBSTITUTE(H34,"+",""))+1),0) -> 0 | N34: =IF(ISNUMBER(SEARCH("PM",H34)),G34/(LEN(H34)-LEN(SUBSTITUTE(H34,"+",""))+1),0) -> 0 | O34: =IF(ISNUMBER(SEARCH("Dev #1",H34)),G34/(LEN(H34)-LEN(SUBSTITUTE(H34,"+",""))+1),0) -> 4 | P34: =IF(ISNUMBER(SEARCH("Dev #2",H34)),G34/(LEN(H34)-LEN(SUBSTITUTE(H34,"+",""))+1),0) -> 0 | Q34: =IF(ISNUMBER(SEARCH("Dev #3",H34)),G34/(LEN(H34)-LEN(SUBSTITUTE(H34,"+",""))+1),0) -> 0 | R34: =IF(ISNUMBER(SEARCH("MKT",H34)),G34/(LEN(H34)-LEN(SUBSTITUTE(H34,"+",""))+1),0) -> 0 | S34: =(M34+N34)*'Parâmetros'!$C$15+(O34+P34+Q34+R34)*'Parâmetros'!$C$16 -> 100 | T34: =S34*I34 -> 100
... A41: 46 | B41: 2.5 | C41: Registrar baseline do escopo e comunicar à equipe | D41: 46129 | E41: 46129 | F41: 1 | G41: 2 | H41: GP | I41: 1 | J41: =IF(I41>=1,"✅ Concluída",IF(I41>0,"🔵 Em execução",IF(E41<'Parâmetros'!$C$10,"🔴 Atrasada","⚪ Não iniciada"))) -> ✅ Concluída | K41: =G41*I41 -> 2 | L41: =IF(E41=D41,IF('Parâmetros'!$C$10>=E41,G41,0),G41*MEDIAN(0,1,('Parâmetros'!$C$10-D41)/(E41-D41))) -> 2 | M41: =IF(ISNUMBER(SEARCH("GP",H41)),G41/(LEN(H41)-LEN(SUBSTITUTE(H41,"+",""))+1),0) -> 2 | N41: =IF(ISNUMBER(SEARCH("PM",H41)),G41/(LEN(H41)-LEN(SUBSTITUTE(H41,"+",""))+1),0) -> 0 | O41: =IF(ISNUMBER(SEARCH("Dev #1",H41)),G41/(LEN(H41)-LEN(SUBSTITUTE(H41,"+",""))+1),0) -> 0 | P41: =IF(ISNUMBER(SEARCH("Dev #2",H41)),G41/(LEN(H41)-LEN(SUBSTITUTE(H41,"+",""))+1),0) -> 0 | Q41: =IF(ISNUMBER(SEARCH("Dev #3",H41)),G41/(LEN(H41)-LEN(SUBSTITUTE(H41,"+",""))+1),0) -> 0 | R41: =IF(ISNUMBER(SEARCH("MKT",H41)),G41/(LEN(H41)-LEN(SUBSTITUTE(H41,"+",""))+1),0) -> 0 | S41: =(M41+N41)*'Parâmetros'!$C$15+(O41+P41+Q41+R41)*'Parâmetros'!$C$16 -> 60 | T41: =S41*I41 -> 60
A42: FASE 3 · Implementação das Funcionalidades
A43: 49 | B43: 3.1 | C43: Implementar interface interativa com menus (RF01–RF04) | D43: 46134 | E43: 46135 | F43: 3 | G43: 24 | H43: Dev #1 | I43: 1 | J43: =IF(I43>=1,"✅ Concluída",IF(I43>0,"🔵 Em execução",IF(E43<'Parâmetros'!$C$10,"🔴 Atrasada","⚪ Não iniciada"))) -> ✅ Concluída | K43: =G43*I43 -> 24 | L43: =IF(E43=D43,IF('Parâmetros'!$C$10>=E43,G43,0),G43*MEDIAN(0,1,('Parâmetros'!$C$10-D43)/(E43-D43))) -> 24 | M43: =IF(ISNUMBER(SEARCH("GP",H43)),G43/(LEN(H43)-LEN(SUBSTITUTE(H43,"+",""))+1),0) -> 0 | N43: =IF(ISNUMBER(SEARCH("PM",H43)),G43/(LEN(H43)-LEN(SUBSTITUTE(H43,"+",""))+1),0) -> 0 | O43: =IF(ISNUMBER(SEARCH("Dev #1",H43)),G43/(LEN(H43)-LEN(SUBSTITUTE(H43,"+",""))+1),0) -> 24 | P43: =IF(ISNUMBER(SEARCH("Dev #2",H43)),G43/(LEN(H43)-LEN(SUBSTITUTE(H43,"+",""))+1),0) -> 0 | Q43: =IF(ISNUMBER(SEARCH("Dev #3",H43)),G43/(LEN(H43)-LEN(SUBSTITUTE(H43,"+",""))+1),0) -> 0 | R43: =IF(ISNUMBER(SEARCH("MKT",H43)),G43/(LEN(H43)-LEN(SUBSTITUTE(H43,"+",""))+1),0) -> 0 | S43: =(M43+N43)*'Parâmetros'!$C$15+(O43+P43+Q43+R43)*'Parâmetros'!$C$16 -> 600 | T43: =S43*I43 -> 600
A44: 50 | B44: 3.1 | C44: Implementar flags não-interativas e modo CI/CD (RF15) | D44: 46136 | E44: 46136 | F44: 2 | G44: 20 | H44: Dev #1 | I44: 1 | J44: =IF(I44>=1,"✅ Concluída",IF(I44>0,"🔵 Em execução",IF(E44<'Parâmetros'!$C$10,"🔴 Atrasada","⚪ Não iniciada"))) -> ✅ Concluída | K44: =G44*I44 -> 20 | L44: =IF(E44=D44,IF('Parâmetros'!$C$10>=E44,G44,0),G44*MEDIAN(0,1,('Parâmetros'!$C$10-D44)/(E44-D44))) -> 20 | M44: =IF(ISNUMBER(SEARCH("GP",H44)),G44/(LEN(H44)-LEN(SUBSTITUTE(H44,"+",""))+1),0) -> 0 | N44: =IF(ISNUMBER(SEARCH("PM",H44)),G44/(LEN(H44)-LEN(SUBSTITUTE(H44,"+",""))+1),0) -> 0 | O44: =IF(ISNUMBER(SEARCH("Dev #1",H44)),G44/(LEN(H44)-LEN(SUBSTITUTE(H44,"+",""))+1),0) -> 20 | P44: =IF(ISNUMBER(SEARCH("Dev #2",H44)),G44/(LEN(H44)-LEN(SUBSTITUTE(H44,"+",""))+1),0) -> 0 | Q44: =IF(ISNUMBER(SEARCH("Dev #3",H44)),G44/(LEN(H44)-LEN(SUBSTITUTE(H44,"+",""))+1),0) -> 0 | R44: =IF(ISNUMBER(SEARCH("MKT",H44)),G44/(LEN(H44)-LEN(SUBSTITUTE(H44,"+",""))+1),0) -> 0 | S44: =(M44+N44)*'Parâmetros'!$C$15+(O44+P44+Q44+R44)*'Parâmetros'!$C$16 -> 500 | T44: =S44*I44 -> 500
A45: 51 | B45: 3.1 | C45: Implementar kybernus doctor — verificação de ambiente | D45: 46137 | E45: 46137 | F45: 2 | G45: 16 | H45: Dev #1 | I45: 1 | J45: =IF(I45>=1,"✅ Concluída",IF(I45>0,"🔵 Em execução",IF(E45<'Parâmetros'!$C$10,"🔴 Atrasada","⚪ Não iniciada"))) -> ✅ Concluída | K45: =G45*I45 -> 16 | L45: =IF(E45=D45,IF('Parâmetros'!$C$10>=E45,G45,0),G45*MEDIAN(0,1,('Parâmetros'!$C$10-D45)/(E45-D45))) -> 16 | M45: =IF(ISNUMBER(SEARCH("GP",H45)),G45/(LEN(H45)-LEN(SUBSTITUTE(H45,"+",""))+1),0) -> 0 | N45: =IF(ISNUMBER(SEARCH("PM",H45)),G45/(LEN(H45)-LEN(SUBSTITUTE(H45,"+",""))+1),0) -> 0 | O45: =IF(ISNUMBER(SEARCH("Dev #1",H45)),G45/(LEN(H45)-LEN(SUBSTITUTE(H45,"+",""))+1),0) -> 16 | P45: =IF(ISNUMBER(SEARCH("Dev #2",H45)),G45/(LEN(H45)-LEN(SUBSTITUTE(H45,"+",""))+1),0) -> 0 | Q45: =IF(ISNUMBER(SEARCH("Dev #3",H45)),G45/(LEN(H45)-LEN(SUBSTITUTE(H45,"+",""))+1),0) -> 0 | R45: =IF(ISNUMBER(SEARCH("MKT",H45)),G45/(LEN(H45)-LEN(SUBSTITUTE(H45,"+",""))+1),0) -> 0 | S45: =(M45+N45)*'Parâmetros'!$C$15+(O45+P45+Q45+R45)*'Parâmetros'!$C$16 -> 400 | T45: =S45*I45 -> 400
A46: 53 | B46: 3.2 | C46: Implementar geração de estrutura por stack + arquitetura | D46: 46140 | E46: 46144 | F46: 4 | G46: 32 | H46: Dev #1 | I46: 1 | J46: =IF(I46>=1,"✅ Concluída",IF(I46>0,"🔵 Em execução",IF(E46<'Parâmetros'!$C$10,"🔴 Atrasada","⚪ Não iniciada"))) -> ✅ Concluída | K46: =G46*I46 -> 32 | L46: =IF(E46=D46,IF('Parâmetros'!$C$10>=E46,G46,0),G46*MEDIAN(0,1,('Parâmetros'!$C$10-D46)/(E46-D46))) -> 32 | M46: =IF(ISNUMBER(SEARCH("GP",H46)),G46/(LEN(H46)-LEN(SUBSTITUTE(H46,"+",""))+1),0) -> 0 | N46: =IF(ISNUMBER(SEARCH("PM",H46)),G46/(LEN(H46)-LEN(SUBSTITUTE(H46,"+",""))+1),0) -> 0 | O46: =IF(ISNUMBER(SEARCH("Dev #1",H46)),G46/(LEN(H46)-LEN(SUBSTITUTE(H46,"+",""))+1),0) -> 32 | P46: =IF(ISNUMBER(SEARCH("Dev #2",H46)),G46/(LEN(H46)-LEN(SUBSTITUTE(H46,"+",""))+1),0) -> 0 | Q46: =IF(ISNUMBER(SEARCH("Dev #3",H46)),G46/(LEN(H46)-LEN(SUBSTITUTE(H46,"+",""))+1),0) -> 0 | R46: =IF(ISNUMBER(SEARCH("MKT",H46)),G46/(LEN(H46)-LEN(SUBSTITUTE(H46,"+",""))+1),0) -> 0 | S46: =(M46+N46)*'Parâmetros'!$C$15+(O46+P46+Q46+R46)*'Parâmetros'!$C$16 -> 800 | T46: =S46*I46 -> 800
A47: 54 | B47: 3.2 | C47: Implementar templates Node.js+Express e NestJS (RF21) | D47: 46147 | E47: 46147 | F47: 2 | G47: 16 | H47: Dev #1 | I47: 1 | J47: =IF(I47>=1,"✅ Concluída",IF(I47>0,"🔵 Em execução",IF(E47<'Parâmetros'!$C$10,"🔴 Atrasada","⚪ Não iniciada"))) -> ✅ Concluída | K47: =G47*I47 -> 16 | L47: =IF(E47=D47,IF('Parâmetros'!$C$10>=E47,G47,0),G47*MEDIAN(0,1,('Parâmetros'!$C$10-D47)/(E47-D47))) -> 16 | M47: =IF(ISNUMBER(SEARCH("GP",H47)),G47/(LEN(H47)-LEN(SUBSTITUTE(H47,"+",""))+1),0) -> 0 | N47: =IF(ISNUMBER(SEARCH("PM",H47)),G47/(LEN(H47)-LEN(SUBSTITUTE(H47,"+",""))+1),0) -> 0 | O47: =IF(ISNUMBER(SEARCH("Dev #1",H47)),G47/(LEN(H47)-LEN(SUBSTITUTE(H47,"+",""))+1),0) -> 16 | P47: =IF(ISNUMBER(SEARCH("Dev #2",H47)),G47/(LEN(H47)-LEN(SUBSTITUTE(H47,"+",""))+1),0) -> 0 | Q47: =IF(ISNUMBER(SEARCH("Dev #3",H47)),G47/(LEN(H47)-LEN(SUBSTITUTE(H47,"+",""))+1),0) -> 0 | R47: =IF(ISNUMBER(SEARCH("MKT",H47)),G47/(LEN(H47)-LEN(SUBSTITUTE(H47,"+",""))+1),0) -> 0 | S47: =(M47+N47)*'Parâmetros'!$C$15+(O47+P47+Q47+R47)*'Parâmetros'!$C$16 -> 400 | T47: =S47*I47 -> 400
A48: 55 | B48: 3.2 | C48: Implementar templates FastAPI e Spring Boot (RF22,RF23) | D48: 46147 | E48: 46147 | F48: 2 | G48: 16 | H48: Dev #2 | I48: 1 | J48: =IF(I48>=1,"✅ Concluída",IF(I48>0,"🔵 Em execução",IF(E48<'Parâmetros'!$C$10,"🔴 Atrasada","⚪ Não iniciada"))) -> ✅ Concluída | K48: =G48*I48 -> 16 | L48: =IF(E48=D48,IF('Parâmetros'!$C$10>=E48,G48,0),G48*MEDIAN(0,1,('Parâmetros'!$C$10-D48)/(E48-D48))) -> 16 | M48: =IF(ISNUMBER(SEARCH("GP",H48)),G48/(LEN(H48)-LEN(SUBSTITUTE(H48,"+",""))+1),0) -> 0 | N48: =IF(ISNUMBER(SEARCH("PM",H48)),G48/(LEN(H48)-LEN(SUBSTITUTE(H48,"+",""))+1),0) -> 0 | O48: =IF(ISNUMBER(SEARCH("Dev #1",H48)),G48/(LEN(H48)-LEN(SUBSTITUTE(H48,"+",""))+1),0) -> 0 | P48: =IF(ISNUMBER(SEARCH("Dev #2",H48)),G48/(LEN(H48)-LEN(SUBSTITUTE(H48,"+",""))+1),0) -> 16 | Q48: =IF(ISNUMBER(SEARCH("Dev #3",H48)),G48/(LEN(H48)-LEN(SUBSTITUTE(H48,"+",""))+1),0) -> 0 | R48: =IF(ISNUMBER(SEARCH("MKT",H48)),G48/(LEN(H48)-LEN(SUBSTITUTE(H48,"+",""))+1),0) -> 0 | S48: =(M48+N48)*'Parâmetros'!$C$15+(O48+P48+Q48+R48)*'Parâmetros'!$C$16 -> 400 | T48: =S48*I48 -> 400
A49: 56 | B49: 3.2 | C49: Implementar templates Next.js e n8n | D49: 46148 | E49: 46148 | F49: 2 | G49: 20 | H49: Dev #2 | I49: 1 | J49: =IF(I49>=1,"✅ Concluída",IF(I49>0,"🔵 Em execução",IF(E49<'Parâmetros'!$C$10,"🔴 Atrasada","⚪ Não iniciada"))) -> ✅ Concluída | K49: =G49*I49 -> 20 | L49: =IF(E49=D49,IF('Parâmetros'!$C$10>=E49,G49,0),G49*MEDIAN(0,1,('Parâmetros'!$C$10-D49)/(E49-D49))) -> 20 | M49: =IF(ISNUMBER(SEARCH("GP",H49)),G49/(LEN(H49)-LEN(SUBSTITUTE(H49,"+",""))+1),0) -> 0 | N49: =IF(ISNUMBER(SEARCH("PM",H49)),G49/(LEN(H49)-LEN(SUBSTITUTE(H49,"+",""))+1),0) -> 0 | O49: =IF(ISNUMBER(SEARCH("Dev #1",H49)),G49/(LEN(H49)-LEN(SUBSTITUTE(H49,"+",""))+1),0) -> 0 | P49: =IF(ISNUMBER(SEARCH("Dev #2",H49)),G49/(LEN(H49)-LEN(SUBSTITUTE(H49,"+",""))+1),0) -> 20 | Q49: =IF(ISNUMBER(SEARCH("Dev #3",H49)),G49/(LEN(H49)-LEN(SUBSTITUTE(H49,"+",""))+1),0) -> 0 | R49: =IF(ISNUMBER(SEARCH("MKT",H49)),G49/(LEN(H49)-LEN(SUBSTITUTE(H49,"+",""))+1),0) -> 0 | S49: =(M49+N49)*'Parâmetros'!$C$15+(O49+P49+Q49+R49)*'Parâmetros'!$C$16 -> 500 | T49: =S49*I49 -> 500
A50: 57 | B50: 3.2 | C50: Gerar arquivos base: .env, ESLint, Prettier (RF20) | D50: 46148 | E50: 46148 | F50: 2 | G50: 16 | H50: Dev #1 | I50: 1 | J50: =IF(I50>=1,"✅ Concluída",IF(I50>0,"🔵 Em execução",IF(E50<'Parâmetros'!$C$10,"🔴 Atrasada","⚪ Não iniciada"))) -> ✅ Concluída | K50: =G50*I50 -> 16 | L50: =IF(E50=D50,IF('Parâmetros'!$C$10>=E50,G50,0),G50*MEDIAN(0,1,('Parâmetros'!$C$10-D50)/(E50-D50))) -> 16 | M50: =IF(ISNUMBER(SEARCH("GP",H50)),G50/(LEN(H50)-LEN(SUBSTITUTE(H50,"+",""))+1),0) -> 0 | N50: =IF(ISNUMBER(SEARCH("PM",H50)),G50/(LEN(H50)-LEN(SUBSTITUTE(H50,"+",""))+1),0) -> 0 | O50: =IF(ISNUMBER(SEARCH("Dev #1",H50)),G50/(LEN(H50)-LEN(SUBSTITUTE(H50,"+",""))+1),0) -> 16 | P50: =IF(ISNUMBER(SEARCH("Dev #2",H50)),G50/(LEN(H50)-LEN(SUBSTITUTE(H50,"+",""))+1),0) -> 0 | Q50: =IF(ISNUMBER(SEARCH("Dev #3",H50)),G50/(LEN(H50)-LEN(SUBSTITUTE(H50,"+",""))+1),0) -> 0 | R50: =IF(ISNUMBER(SEARCH("MKT",H50)),G50/(LEN(H50)-LEN(SUBSTITUTE(H50,"+",""))+1),0) -> 0 | S50: =(M50+N50)*'Parâmetros'!$C$15+(O50+P50+Q50+R50)*'Parâmetros'!$C$16 -> 400 | T50: =S50*I50 -> 400
A51: 59 | B51: 3.3 | C51: Implementar geração de Docker + GH Actions + Terraform | D51: 46149 | E51: 46154 | F51: 3 | G51: 24 | H51: Dev #2 | I51: 1 | J51: =IF(I51>=1,"✅ Concluída",IF(I51>0,"🔵 Em execução",IF(E51<'Parâmetros'!$C$10,"🔴 Atrasada","⚪ Não iniciada"))) -> ✅ Concluída | K51: =G51*I51 -> 24 | L51: =IF(E51=D51,IF('Parâmetros'!$C$10>=E51,G51,0),G51*MEDIAN(0,1,('Parâmetros'!$C$10-D51)/(E51-D51))) -> 24 | M51: =IF(ISNUMBER(SEARCH("GP",H51)),G51/(LEN(H51)-LEN(SUBSTITUTE(H51,"+",""))+1),0) -> 0 | N51: =IF(ISNUMBER(SEARCH("PM",H51)),G51/(LEN(H51)-LEN(SUBSTITUTE(H51,"+",""))+1),0) -> 0 | O51: =IF(ISNUMBER(SEARCH("Dev #1",H51)),G51/(LEN(H51)-LEN(SUBSTITUTE(H51,"+",""))+1),0) -> 0 | P51: =IF(ISNUMBER(SEARCH("Dev #2",H51)),G51/(LEN(H51)-LEN(SUBSTITUTE(H51,"+",""))+1),0) -> 24 | Q51: =IF(ISNUMBER(SEARCH("Dev #3",H51)),G51/(LEN(H51)-LEN(SUBSTITUTE(H51,"+",""))+1),0) -> 0 | R51: =IF(ISNUMBER(SEARCH("MKT",H51)),G51/(LEN(H51)-LEN(SUBSTITUTE(H51,"+",""))+1),0) -> 0 | S51: =(M51+N51)*'Parâmetros'!$C$15+(O51+P51+Q51+R51)*'Parâmetros'!$C$16 -> 600 | T51: =S51*I51 -> 600
A52: 60 | B52: 3.3 | C52: Implementar kybernus deploy (Vercel, Railway…) (RF13) | D52: 46155 | E52: 46155 | F52: 2 | G52: 20 | H52: Dev #2 | I52: 1 | J52: =IF(I52>=1,"✅ Concluída",IF(I52>0,"🔵 Em execução",IF(E52<'Parâmetros'!$C$10,"🔴 Atrasada","⚪ Não iniciada"))) -> ✅ Concluída | K52: =G52*I52 -> 20 | L52: =IF(E52=D52,IF('Parâmetros'!$C$10>=E52,G52,0),G52*MEDIAN(0,1,('Parâmetros'!$C$10-D52)/(E52-D52))) -> 20 | M52: =IF(ISNUMBER(SEARCH("GP",H52)),G52/(LEN(H52)-LEN(SUBSTITUTE(H52,"+",""))+1),0) -> 0 | N52: =IF(ISNUMBER(SEARCH("PM",H52)),G52/(LEN(H52)-LEN(SUBSTITUTE(H52,"+",""))+1),0) -> 0 | O52: =IF(ISNUMBER(SEARCH("Dev #1",H52)),G52/(LEN(H52)-LEN(SUBSTITUTE(H52,"+",""))+1),0) -> 0 | P52: =IF(ISNUMBER(SEARCH("Dev #2",H52)),G52/(LEN(H52)-LEN(SUBSTITUTE(H52,"+",""))+1),0) -> 20 | Q52: =IF(ISNUMBER(SEARCH("Dev #3",H52)),G52/(LEN(H52)-LEN(SUBSTITUTE(H52,"+",""))+1),0) -> 0 | R52: =IF(ISNUMBER(SEARCH("MKT",H52)),G52/(LEN(H52)-LEN(SUBSTITUTE(H52,"+",""))+1),0) -> 0 | S52: =(M52+N52)*'Parâmetros'!$C$15+(O52+P52+Q52+R52)*'Parâmetros'!$C$16 -> 500 | T52: =S52*I52 -> 500
A53: 61 | B53: 3.3 | C53: Implementar suporte a template customizado via GitHub | D53: 46156 | E53: 46156 | F53: 2 | G53: 16 | H53: Dev #2 | I53: 1 | J53: =IF(I53>=1,"✅ Concluída",IF(I53>0,"🔵 Em execução",IF(E53<'Parâmetros'!$C$10,"🔴 Atrasada","⚪ Não iniciada"))) -> ✅ Concluída | K53: =G53*I53 -> 16 | L53: =IF(E53=D53,IF('Parâmetros'!$C$10>=E53,G53,0),G53*MEDIAN(0,1,('Parâmetros'!$C$10-D53)/(E53-D53))) -> 16 | M53: =IF(ISNUMBER(SEARCH("GP",H53)),G53/(LEN(H53)-LEN(SUBSTITUTE(H53,"+",""))+1),0) -> 0 | N53: =IF(ISNUMBER(SEARCH("PM",H53)),G53/(LEN(H53)-LEN(SUBSTITUTE(H53,"+",""))+1),0) -> 0 | O53: =IF(ISNUMBER(SEARCH("Dev #1",H53)),G53/(LEN(H53)-LEN(SUBSTITUTE(H53,"+",""))+1),0) -> 0 | P53: =IF(ISNUMBER(SEARCH("Dev #2",H53)),G53/(LEN(H53)-LEN(SUBSTITUTE(H53,"+",""))+1),0) -> 16 | Q53: =IF(ISNUMBER(SEARCH("Dev #3",H53)),G53/(LEN(H53)-LEN(SUBSTITUTE(H53,"+",""))+1),0) -> 0 | R53: =IF(ISNUMBER(SEARCH("MKT",H53)),G53/(LEN(H53)-LEN(SUBSTITUTE(H53,"+",""))+1),0) -> 0 | S53: =(M53+N53)*'Parâmetros'!$C$15+(O53+P53+Q53+R53)*'Parâmetros'!$C$16 -> 400 | T53: =S53*I53 -> 400
A54: 63 | B54: 3.4 | C54: Implementar kybernus add swagger, redis (RF08,RF09) | D54: 46157 | E54: 46158 | F54: 3 | G54: 24 | H54: Dev #2 | I54: 0.7 | J54: =IF(I54>=1,"✅ Concluída",IF(I54>0,"🔵 Em execução",IF(E54<'Parâmetros'!$C$10,"🔴 Atrasada","⚪ Não iniciada"))) -> 🔵 Em execução | K54: =G54*I54 -> 16.8 | L54: =IF(E54=D54,IF('Parâmetros'!$C$10>=E54,G54,0),G54*MEDIAN(0,1,('Parâmetros'!$C$10-D54)/(E54-D54))) -> 24 | M54: =IF(ISNUMBER(SEARCH("GP",H54)),G54/(LEN(H54)-LEN(SUBSTITUTE(H54,"+",""))+1),0) -> 0 | N54: =IF(ISNUMBER(SEARCH("PM",H54)),G54/(LEN(H54)-LEN(SUBSTITUTE(H54,"+",""))+1),0) -> 0 | O54: =IF(ISNUMBER(SEARCH("Dev #1",H54)),G54/(LEN(H54)-LEN(SUBSTITUTE(H54,"+",""))+1),0) -> 0 | P54: =IF(ISNUMBER(SEARCH("Dev #2",H54)),G54/(LEN(H54)-LEN(SUBSTITUTE(H54,"+",""))+1),0) -> 24 | Q54: =IF(ISNUMBER(SEARCH("Dev #3",H54)),G54/(LEN(H54)-LEN(SUBSTITUTE(H54,"+",""))+1),0) -> 0 | R54: =IF(ISNUMBER(SEARCH("MKT",H54)),G54/(LEN(H54)-LEN(SUBSTITUTE(H54,"+",""))+1),0) -> 0 | S54: =(M54+N54)*'Parâmetros'!$C$15+(O54+P54+Q54+R54)*'Parâmetros'!$C$16 -> 600 | T54: =S54*I54 -> 420
... A66: 120 | B66: 3.8 | C66: Mapear novo perfil de acesso (MUD-02) | D66: 46174 | E66: 46175 | F66: 3 | G66: 4 | H66: Dev #2 | I66: 0 | J66: =IF(I66>=1,"✅ Concluída",IF(I66>0,"🔵 Em execução",IF(E66<'Parâmetros'!$C$10,"🔴 Atrasada","⚪ Não iniciada"))) -> ⚪ Não iniciada | K66: =G66*I66 -> 0 | L66: =IF(E66=D66,IF('Parâmetros'!$C$10>=E66,G66,0),G66*MEDIAN(0,1,('Parâmetros'!$C$10-D66)/(E66-D66))) -> 0 | M66: =IF(ISNUMBER(SEARCH("GP",H66)),G66/(LEN(H66)-LEN(SUBSTITUTE(H66,"+",""))+1),0) -> 0 | N66: =IF(ISNUMBER(SEARCH("PM",H66)),G66/(LEN(H66)-LEN(SUBSTITUTE(H66,"+",""))+1),0) -> 0 | O66: =IF(ISNUMBER(SEARCH("Dev #1",H66)),G66/(LEN(H66)-LEN(SUBSTITUTE(H66,"+",""))+1),0) -> 0 | P66: =IF(ISNUMBER(SEARCH("Dev #2",H66)),G66/(LEN(H66)-LEN(SUBSTITUTE(H66,"+",""))+1),0) -> 4 | Q66: =IF(ISNUMBER(SEARCH("Dev #3",H66)),G66/(LEN(H66)-LEN(SUBSTITUTE(H66,"+",""))+1),0) -> 0 | R66: =IF(ISNUMBER(SEARCH("MKT",H66)),G66/(LEN(H66)-LEN(SUBSTITUTE(H66,"+",""))+1),0) -> 0 | S66: =(M66+N66)*'Parâmetros'!$C$15+(O66+P66+Q66+R66)*'Parâmetros'!$C$16 -> 100 | T66: =S66*I66 -> 0
A67: 121 | B67: 3.9 | C67: Implementar novo perfil de acesso (MUD-02) | D67: 46175 | E67: 46177 | F67: 3 | G67: 15 | H67: Dev #2 | I67: 0 | J67: =IF(I67>=1,"✅ Concluída",IF(I67>0,"🔵 Em execução",IF(E67<'Parâmetros'!$C$10,"🔴 Atrasada","⚪ Não iniciada"))) -> ⚪ Não iniciada | K67: =G67*I67 -> 0 | T67: =S67*I67 -> 0
A68: 122 | B68: 3.8 | C68: Implementar regras de permissão (MUD-02) | D68: 46177 | E68: 46178 | F68: 2 | G68: 10 | H68: Dev #2 | I68: 0 | J68: =IF(I68>=1,"✅ Concluída",IF(I68>0,"🔵 Em execução",IF(E68<'Parâmetros'!$C$10,"🔴 Atrasada","⚪ Não iniciada"))) -> ⚪ Não iniciada | K68: =G68*I68 -> 0 | L68: =IF(E68=D68,IF('Parâmetros'!$C$10>=E68,G68,0),G68*MEDIAN(0,1,('Parâmetros'!$C$10-D68)/(E68-D68))) -> 0 | M68: =IF(ISNUMBER(SEARCH("GP",H68)),G68/(LEN(H68)-LEN(SUBSTITUTE(H68,"+",""))+1),0) -> 0 | N68: =IF(ISNUMBER(SEARCH("PM",H68)),G68/(LEN(H68)-LEN(SUBSTITUTE(H68,"+",""))+1),0) -> 0 | O68: =IF(ISNUMBER(SEARCH("Dev #1",H68)),G68/(LEN(H68)-LEN(SUBSTITUTE(H68,"+",""))+1),0) -> 0 | P68: =IF(ISNUMBER(SEARCH("Dev #2",H68)),G68/(LEN(H68)-LEN(SUBSTITUTE(H68,"+",""))+1),0) -> 10 | Q68: =IF(ISNUMBER(SEARCH("Dev #3",H68)),G68/(LEN(H68)-LEN(SUBSTITUTE(H68,"+",""))+1),0) -> 0 | R68: =IF(ISNUMBER(SEARCH("MKT",H68)),G68/(LEN(H68)-LEN(SUBSTITUTE(H68,"+",""))+1),0) -> 0 | S68: =(M68+N68)*'Parâmetros'!$C$15+(O68+P68+Q68+R68)*'Parâmetros'!$C$16 -> 250 | T68: =S68*I68 -> 0
A69: 123 | B69: 3.8 | C69: Ajustes de segurança e revisão (MUD-02) | D69: 46181 | E69: 46181 | F69: 1 | G69: 10 | H69: Dev #2 | I69: 0 | J69: =IF(I69>=1,"✅ Concluída",IF(I69>0,"🔵 Em execução",IF(E69<'Parâmetros'!$C$10,"🔴 Atrasada","⚪ Não iniciada"))) -> ⚪ Não iniciada | K69: =G69*I69 -> 0 | L69: =IF(E69=D69,IF('Parâmetros'!$C$10>=E69,G69,0),G69*MEDIAN(0,1,('Parâmetros'!$C$10-D69)/(E69-D69))) -> 0 | M69: =IF(ISNUMBER(SEARCH("GP",H69)),G69/(LEN(H69)-LEN(SUBSTITUTE(H69,"+",""))+1),0) -> 0 | N69: =IF(ISNUMBER(SEARCH("PM",H69)),G69/(LEN(H69)-LEN(SUBSTITUTE(H69,"+",""))+1),0) -> 0 | O69: =IF(ISNUMBER(SEARCH("Dev #1",H69)),G69/(LEN(H69)-LEN(SUBSTITUTE(H69,"+",""))+1),0) -> 0 | P69: =IF(ISNUMBER(SEARCH("Dev #2",H69)),G69/(LEN(H69)-LEN(SUBSTITUTE(H69,"+",""))+1),0) -> 10 | Q69: =IF(ISNUMBER(SEARCH("Dev #3",H69)),G69/(LEN(H69)-LEN(SUBSTITUTE(H69,"+",""))+1),0) -> 0 | R69: =IF(ISNUMBER(SEARCH("MKT",H69)),G69/(LEN(H69)-LEN(SUBSTITUTE(H69,"+",""))+1),0) -> 0 | S69: =(M69+N69)*'Parâmetros'!$C$15+(O69+P69+Q69+R69)*'Parâmetros'!$C$16 -> 250 | T69: =S69*I69 -> 0
A70: FASE 4 · Testes e Documentação
A71: 81 | B71: 4.1 | C71: Escrever testes unitários por módulo (RNF04) | D71: 46181 | E71: 46181 | F71: 2 | G71: 40 | H71: Dev #1+Dev #2 | I71: 0 | J71: =IF(I71>=1,"✅ Concluída",IF(I71>0,"🔵 Em execução",IF(E71<'Parâmetros'!$C$10,"🔴 Atrasada","⚪ Não iniciada"))) -> ⚪ Não iniciada | K71: =G71*I71 -> 0 | L71: =IF(E71=D71,IF('Parâmetros'!$C$10>=E71,G71,0),G71*MEDIAN(0,1,('Parâmetros'!$C$10-D71)/(E71-D71))) -> 0 | M71: =IF(ISNUMBER(SEARCH("GP",H71)),G71/(LEN(H71)-LEN(SUBSTITUTE(H71,"+",""))+1),0) -> 0 | N71: =IF(ISNUMBER(SEARCH("PM",H71)),G71/(LEN(H71)-LEN(SUBSTITUTE(H71,"+",""))+1),0) -> 0 | O71: =IF(ISNUMBER(SEARCH("Dev #1",H71)),G71/(LEN(H71)-LEN(SUBSTITUTE(H71,"+",""))+1),0) -> 20 | P71: =IF(ISNUMBER(SEARCH("Dev #2",H71)),G71/(LEN(H71)-LEN(SUBSTITUTE(H71,"+",""))+1),0) -> 20 | Q71: =IF(ISNUMBER(SEARCH("Dev #3",H71)),G71/(LEN(H71)-LEN(SUBSTITUTE(H71,"+",""))+1),0) -> 0 | R71: =IF(ISNUMBER(SEARCH("MKT",H71)),G71/(LEN(H71)-LEN(SUBSTITUTE(H71,"+",""))+1),0) -> 0 | S71: =(M71+N71)*'Parâmetros'!$C$15+(O71+P71+Q71+R71)*'Parâmetros'!$C$16 -> 1000 | T71: =S71*I71 -> 0
A72: 82 | B72: 4.1 | C72: Escrever testes de integração entre módulos | D72: 46182 | E72: 46182 | F72: 2 | G72: 16 | H72: Dev #2 | I72: 0 | J72: =IF(I72>=1,"✅ Concluída",IF(I72>0,"🔵 Em execução",IF(E72<'Parâmetros'!$C$10,"🔴 Atrasada","⚪ Não iniciada"))) -> ⚪ Não iniciada | K72: =G72*I72 -> 0 | L72: =IF(E72=D72,IF('Parâmetros'!$C$10>=E72,G72,0),G72*MEDIAN(0,1,('Parâmetros'!$C$10-D72)/(E72-D72))) -> 0 | M72: =IF(ISNUMBER(SEARCH("GP",H72)),G72/(LEN(H72)-LEN(SUBSTITUTE(H72,"+",""))+1),0) -> 0 | N72: =IF(ISNUMBER(SEARCH("PM",H72)),G72/(LEN(H72)-LEN(SUBSTITUTE(H72,"+",""))+1),0) -> 0 | O72: =IF(ISNUMBER(SEARCH("Dev #1",H72)),G72/(LEN(H72)-LEN(SUBSTITUTE(H72,"+",""))+1),0) -> 0 | P72: =IF(ISNUMBER(SEARCH("Dev #2",H72)),G72/(LEN(H72)-LEN(SUBSTITUTE(H72,"+",""))+1),0) -> 16 | Q72: =IF(ISNUMBER(SEARCH("Dev #3",H72)),G72/(LEN(H72)-LEN(SUBSTITUTE(H72,"+",""))+1),0) -> 0 | R72: =IF(ISNUMBER(SEARCH("MKT",H72)),G72/(LEN(H72)-LEN(SUBSTITUTE(H72,"+",""))+1),0) -> 0 | S72: =(M72+N72)*'Parâmetros'!$C$15+(O72+P72+Q72+R72)*'Parâmetros'!$C$16 -> 400 | T72: =S72*I72 -> 0
A73: 83 | B73: 4.1 | C73: Validar sintaxe de arquivos gerados | D73: 46182 | E73: 46182 | F73: 2 | G73: 16 | H73: Dev #1 | I73: 0 | J73: =IF(I73>=1,"✅ Concluída",IF(I73>0,"🔵 Em execução",IF(E73<'Parâmetros'!$C$10,"🔴 Atrasada","⚪ Não iniciada"))) -> ⚪ Não iniciada | K73: =G73*I73 -> 0 | L73: =IF(E73=D73,IF('Parâmetros'!$C$10>=E73,G73,0),G73*MEDIAN(0,1,('Parâmetros'!$C$10-D73)/(E73-D73))) -> 0 | M73: =IF(ISNUMBER(SEARCH("GP",H73)),G73/(LEN(H73)-LEN(SUBSTITUTE(H73,"+",""))+1),0) -> 0 | N73: =IF(ISNUMBER(SEARCH("PM",H73)),G73/(LEN(H73)-LEN(SUBSTITUTE(H73,"+",""))+1),0) -> 0 | O73: =IF(ISNUMBER(SEARCH("Dev #1",H73)),G73/(LEN(H73)-LEN(SUBSTITUTE(H73,"+",""))+1),0) -> 16 | P73: =IF(ISNUMBER(SEARCH("Dev #2",H73)),G73/(LEN(H73)-LEN(SUBSTITUTE(H73,"+",""))+1),0) -> 0 | Q73: =IF(ISNUMBER(SEARCH("Dev #3",H73)),G73/(LEN(H73)-LEN(SUBSTITUTE(H73,"+",""))+1),0) -> 0 | R73: =IF(ISNUMBER(SEARCH("MKT",H73)),G73/(LEN(H73)-LEN(SUBSTITUTE(H73,"+",""))+1),0) -> 0 | S73: =(M73+N73)*'Parâmetros'!$C$15+(O73+P73+Q73+R73)*'Parâmetros'!$C$16 -> 400 | T73: =S73*I73 -> 0
A74: 85 | B74: 4.2 | C74: Recrutar ≥5 desenvolvedores externos para testes | D74: 46183 | E74: 46183 | F74: 2 | G74: 4 | H74: GP | I74: 0 | J74: =IF(I74>=1,"✅ Concluída",IF(I74>0,"🔵 Em execução",IF(E74<'Parâmetros'!$C$10,"🔴 Atrasada","⚪ Não iniciada"))) -> ⚪ Não iniciada | K74: =G74*I74 -> 0 | L74: =IF(E74=D74,IF('Parâmetros'!$C$10>=E74,G74,0),G74*MEDIAN(0,1,('Parâmetros'!$C$10-D74)/(E74-D74))) -> 0 | M74: =IF(ISNUMBER(SEARCH("GP",H74)),G74/(LEN(H74)-LEN(SUBSTITUTE(H74,"+",""))+1),0) -> 4 | N74: =IF(ISNUMBER(SEARCH("PM",H74)),G74/(LEN(H74)-LEN(SUBSTITUTE(H74,"+",""))+1),0) -> 0 | O74: =IF(ISNUMBER(SEARCH("Dev #1",H74)),G74/(LEN(H74)-LEN(SUBSTITUTE(H74,"+",""))+1),0) -> 0 | P74: =IF(ISNUMBER(SEARCH("Dev #2",H74)),G74/(LEN(H74)-LEN(SUBSTITUTE(H74,"+",""))+1),0) -> 0 | Q74: =IF(ISNUMBER(SEARCH("Dev #3",H74)),G74/(LEN(H74)-LEN(SUBSTITUTE(H74,"+",""))+1),0) -> 0 | R74: =IF(ISNUMBER(SEARCH("MKT",H74)),G74/(LEN(H74)-LEN(SUBSTITUTE(H74,"+",""))+1),0) -> 0 | S74: =(M74+N74)*'Parâmetros'!$C$15+(O74+P74+Q74+R74)*'Parâmetros'!$C$16 -> 120 | T74: =S74*I74 -> 0
A75: 86 | B75: 4.2 | C75: Conduzir sessões de instalação e geração sem auxílio | D75: 46184 | E75: 46184 | F75: 1 | G75: 28 | H75: Dev #1+Dev #2+GP | I75: 0 | J75: =IF(I75>=1,"✅ Concluída",IF(I75>0,"🔵 Em execução",IF(E75<'Parâmetros'!$C$10,"🔴 Atrasada","⚪ Não iniciada"))) -> ⚪ Não iniciada | K75: =G75*I75 -> 0 | L75: =IF(E75=D75,IF('Parâmetros'!$C$10>=E75,G75,0),G75*MEDIAN(0,1,('Parâmetros'!$C$10-D75)/(E75-D75))) -> 0 | M75: =IF(ISNUMBER(SEARCH("GP",H75)),G75/(LEN(H75)-LEN(SUBSTITUTE(H75,"+",""))+1),0) -> 9.3333333 | N75: =IF(ISNUMBER(SEARCH("PM",H75)),G75/(LEN(H75)-LEN(SUBSTITUTE(H75,"+",""))+1),0) -> 0 | O75: =IF(ISNUMBER(SEARCH("Dev #1",H75)),G75/(LEN(H75)-LEN(SUBSTITUTE(H75,"+",""))+1),0) -> 9.3333333 | P75: =IF(ISNUMBER(SEARCH("Dev #2",H75)),G75/(LEN(H75)-LEN(SUBSTITUTE(H75,"+",""))+1),0) -> 9.3333333 | Q75: =IF(ISNUMBER(SEARCH("Dev #3",H75)),G75/(LEN(H75)-LEN(SUBSTITUTE(H75,"+",""))+1),0) -> 0 | R75: =IF(ISNUMBER(SEARCH("MKT",H75)),G75/(LEN(H75)-LEN(SUBSTITUTE(H75,"+",""))+1),0) -> 0 | S75: =(M75+N75)*'Parâmetros'!$C$15+(O75+P75+Q75+R75)*'Parâmetros'!$C$16 -> 746.66667 | T75: =S75*I75 -> 0
A76: 87 | B76: 4.2 | C76: Registrar resultados e validar meta de 80% de sucesso | D76: 46185 | E76: 46185 | F76: 2 | G76: 4 | H76: GP | I76: 0 | J76: =IF(I76>=1,"✅ Concluída",IF(I76>0,"🔵 Em execução",IF(E76<'Parâmetros'!$C$10,"🔴 Atrasada","⚪ Não iniciada"))) -> ⚪ Não iniciada | K76: =G76*I76 -> 0 | L76: =IF(E76=D76,IF('Parâmetros'!$C$10>=E76,G76,0),G76*MEDIAN(0,1,('Parâmetros'!$C$10-D76)/(E76-D76))) -> 0 | M76: =IF(ISNUMBER(SEARCH("GP",H76)),G76/(LEN(H76)-LEN(SUBSTITUTE(H76,"+",""))+1),0) -> 4 | N76: =IF(ISNUMBER(SEARCH("PM",H76)),G76/(LEN(H76)-LEN(SUBSTITUTE(H76,"+",""))+1),0) -> 0 | O76: =IF(ISNUMBER(SEARCH("Dev #1",H76)),G76/(LEN(H76)-LEN(SUBSTITUTE(H76,"+",""))+1),0) -> 0 | P76: =IF(ISNUMBER(SEARCH("Dev #2",H76)),G76/(LEN(H76)-LEN(SUBSTITUTE(H76,"+",""))+1),0) -> 0 | Q76: =IF(ISNUMBER(SEARCH("Dev #3",H76)),G76/(LEN(H76)-LEN(SUBSTITUTE(H76,"+",""))+1),0) -> 0 | R76: =IF(ISNUMBER(SEARCH("MKT",H76)),G76/(LEN(H76)-LEN(SUBSTITUTE(H76,"+",""))+1),0) -> 0 | S76: =(M76+N76)*'Parâmetros'!$C$15+(O76+P76+Q76+R76)*'Parâmetros'!$C$16 -> 120 | T76: =S76*I76 -> 0
A77: 89 | B77: 4.3 | C77: Verificar checklist formal dos critérios do TAP | D77: 46188 | E77: 46190 | F77: 4 | G77: 8 | H77: GP | I77: 0 | J77: =IF(I77>=1,"✅ Concluída",IF(I77>0,"🔵 Em execução",IF(E77<'Parâmetros'!$C$10,"🔴 Atrasada","⚪ Não iniciada"))) -> ⚪ Não iniciada | K77: =G77*I77 -> 0 | L77: =IF(E77=D77,IF('Parâmetros'!$C$10>=E77,G77,0),G77*MEDIAN(0,1,('Parâmetros'!$C$10-D77)/(E77-D77))) -> 0 | M77: =IF(ISNUMBER(SEARCH("GP",H77)),G77/(LEN(H77)-LEN(SUBSTITUTE(H77,"+",""))+1),0) -> 8 | N77: =IF(ISNUMBER(SEARCH("PM",H77)),G77/(LEN(H77)-LEN(SUBSTITUTE(H77,"+",""))+1),0) -> 0 | O77: =IF(ISNUMBER(SEARCH("Dev #1",H77)),G77/(LEN(H77)-LEN(SUBSTITUTE(H77,"+",""))+1),0) -> 0 | P77: =IF(ISNUMBER(SEARCH("Dev #2",H77)),G77/(LEN(H77)-LEN(SUBSTITUTE(H77,"+",""))+1),0) -> 0 | Q77: =IF(ISNUMBER(SEARCH("Dev #3",H77)),G77/(LEN(H77)-LEN(SUBSTITUTE(H77,"+",""))+1),0) -> 0 | R77: =IF(ISNUMBER(SEARCH("MKT",H77)),G77/(LEN(H77)-LEN(SUBSTITUTE(H77,"+",""))+1),0) -> 0 | S77: =(M77+N77)*'Parâmetros'!$C$15+(O77+P77+Q77+R77)*'Parâmetros'!$C$16 -> 240 | T77: =S77*I77 -> 0
A78: 90 | B78: 4.3 | C78: Elaborar relatório de validação interna | D78: 46191 | E78: 46193 | F78: 4 | G78: 8 | H78: GP | I78: 0 | J78: =IF(I78>=1,"✅ Concluída",IF(I78>0,"🔵 Em execução",IF(E78<'Parâmetros'!$C$10,"🔴 Atrasada","⚪ Não iniciada"))) -> ⚪ Não iniciada | K78: =G78*I78 -> 0 | L78: =IF(E78=D78,IF('Parâmetros'!$C$10>=E78,G78,0),G78*MEDIAN(0,1,('Parâmetros'!$C$10-D78)/(E78-D78))) -> 0 | M78: =IF(ISNUMBER(SEARCH("GP",H78)),G78/(LEN(H78)-LEN(SUBSTITUTE(H78,"+",""))+1),0) -> 8 | N78: =IF(ISNUMBER(SEARCH("PM",H78)),G78/(LEN(H78)-LEN(SUBSTITUTE(H78,"+",""))+1),0) -> 0 | O78: =IF(ISNUMBER(SEARCH("Dev #1",H78)),G78/(LEN(H78)-LEN(SUBSTITUTE(H78,"+",""))+1),0) -> 0 | P78: =IF(ISNUMBER(SEARCH("Dev #2",H78)),G78/(LEN(H78)-LEN(SUBSTITUTE(H78,"+",""))+1),0) -> 0 | Q78: =IF(ISNUMBER(SEARCH("Dev #3",H78)),G78/(LEN(H78)-LEN(SUBSTITUTE(H78,"+",""))+1),0) -> 0 | R78: =IF(ISNUMBER(SEARCH("MKT",H78)),G78/(LEN(H78)-LEN(SUBSTITUTE(H78,"+",""))+1),0) -> 0 | S78: =(M78+N78)*'Parâmetros'!$C$15+(O78+P78+Q78+R78)*'Parâmetros'!$C$16 -> 240 | T78: =S78*I78 -> 0
A79: 93 | B79: 4.4 | C79: Elaborar guia de contribuição open-source | D79: 46190 | E79: 46190 | F79: 2 | G79: 14 | H79: Dev #1 | I79: 0 | J79: =IF(I79>=1,"✅ Concluída",IF(I79>0,"🔵 Em execução",IF(E79<'Parâmetros'!$C$10,"🔴 Atrasada","⚪ Não iniciada"))) -> ⚪ Não iniciada | K79: =G79*I79 -> 0 | L79: =IF(E79=D79,IF('Parâmetros'!$C$10>=E79,G79,0),G79*MEDIAN(0,1,('Parâmetros'!$C$10-D79)/(E79-D79))) -> 0 | M79: =IF(ISNUMBER(SEARCH("GP",H79)),G79/(LEN(H79)-LEN(SUBSTITUTE(H79,"+",""))+1),0) -> 0 | N79: =IF(ISNUMBER(SEARCH("PM",H79)),G79/(LEN(H79)-LEN(SUBSTITUTE(H79,"+",""))+1),0) -> 0 | O79: =IF(ISNUMBER(SEARCH("Dev #1",H79)),G79/(LEN(H79)-LEN(SUBSTITUTE(H79,"+",""))+1),0) -> 14 | P79: =IF(ISNUMBER(SEARCH("Dev #2",H79)),G79/(LEN(H79)-LEN(SUBSTITUTE(H79,"+",""))+1),0) -> 0 | Q79: =IF(ISNUMBER(SEARCH("Dev #3",H79)),G79/(LEN(H79)-LEN(SUBSTITUTE(H79,"+",""))+1),0) -> 0 | R79: =IF(ISNUMBER(SEARCH("MKT",H79)),G79/(LEN(H79)-LEN(SUBSTITUTE(H79,"+",""))+1),0) -> 0 | S79: =(M79+N79)*'Parâmetros'!$C$15+(O79+P79+Q79+R79)*'Parâmetros'!$C$16 -> 350 | T79: =S79*I79 -> 0
A80: 94 | B80: 4.4 | C80: Documentar módulos internos | D80: 46196 | E80: 46196 | F80: 2 | G80: 14 | H80: Dev #1 | I80: 0 | J80: =IF(I80>=1,"✅ Concluída",IF(I80>0,"🔵 Em execução",IF(E80<'Parâmetros'!$C$10,"🔴 Atrasada","⚪ Não iniciada"))) -> ⚪ Não iniciada | K80: =G80*I80 -> 0 | L80: =IF(E80=D80,IF('Parâmetros'!$C$10>=E80,G80,0),G80*MEDIAN(0,1,('Parâmetros'!$C$10-D80)/(E80-D80))) -> 0 | M80: =IF(ISNUMBER(SEARCH("GP",H80)),G80/(LEN(H80)-LEN(SUBSTITUTE(H80,"+",""))+1),0) -> 0 | N80: =IF(ISNUMBER(SEARCH("PM",H80)),G80/(LEN(H80)-LEN(SUBSTITUTE(H80,"+",""))+1),0) -> 0 | O80: =IF(ISNUMBER(SEARCH("Dev #1",H80)),G80/(LEN(H80)-LEN(SUBSTITUTE(H80,"+",""))+1),0) -> 14 | P80: =IF(ISNUMBER(SEARCH("Dev #2",H80)),G80/(LEN(H80)-LEN(SUBSTITUTE(H80,"+",""))+1),0) -> 0 | Q80: =IF(ISNUMBER(SEARCH("Dev #3",H80)),G80/(LEN(H80)-LEN(SUBSTITUTE(H80,"+",""))+1),0) -> 0 | R80: =IF(ISNUMBER(SEARCH("MKT",H80)),G80/(LEN(H80)-LEN(SUBSTITUTE(H80,"+",""))+1),0) -> 0 | S80: =(M80+N80)*'Parâmetros'!$C$15+(O80+P80+Q80+R80)*'Parâmetros'!$C$16 -> 350 | T80: =S80*I80 -> 0
A81: 96 | B81: 4.5 | C81: Escrever guia de instalação e uso | D81: 46191 | E81: 46191 | F81: 2 | G81: 20 | H81: Dev #1+PM | I81: 0 | J81: =IF(I81>=1,"✅ Concluída",IF(I81>0,"🔵 Em execução",IF(E81<'Parâmetros'!$C$10,"🔴 Atrasada","⚪ Não iniciada"))) -> ⚪ Não iniciada | K81: =G81*I81 -> 0 | L81: =IF(E81=D81,IF('Parâmetros'!$C$10>=E81,G81,0),G81*MEDIAN(0,1,('Parâmetros'!$C$10-D81)/(E81-D81))) -> 0 | M81: =IF(ISNUMBER(SEARCH("GP",H81)),G81/(LEN(H81)-LEN(SUBSTITUTE(H81,"+",""))+1),0) -> 0 | N81: =IF(ISNUMBER(SEARCH("PM",H81)),G81/(LEN(H81)-LEN(SUBSTITUTE(H81,"+",""))+1),0) -> 10 | O81: =IF(ISNUMBER(SEARCH("Dev #1",H81)),G81/(LEN(H81)-LEN(SUBSTITUTE(H81,"+",""))+1),0) -> 10 | P81: =IF(ISNUMBER(SEARCH("Dev #2",H81)),G81/(LEN(H81)-LEN(SUBSTITUTE(H81,"+",""))+1),0) -> 0 | Q81: =IF(ISNUMBER(SEARCH("Dev #3",H81)),G81/(LEN(H81)-LEN(SUBSTITUTE(H81,"+",""))+1),0) -> 0 | R81: =IF(ISNUMBER(SEARCH("MKT",H81)),G81/(LEN(H81)-LEN(SUBSTITUTE(H81,"+",""))+1),0) -> 0 | S81: =(M81+N81)*'Parâmetros'!$C$15+(O81+P81+Q81+R81)*'Parâmetros'!$C$16 -> 550 | T81: =S81*I81 -> 0
A82: 97 | B82: 4.5 | C82: Documentar referência de comandos | D82: 46192 | E82: 46192 | F82: 2 | G82: 20 | H82: Dev #1 | I82: 0 | J82: =IF(I82>=1,"✅ Concluída",IF(I82>0,"🔵 Em execução",IF(E82<'Parâmetros'!$C$10,"🔴 Atrasada","⚪ Não iniciada"))) -> ⚪ Não iniciada | K82: =G82*I82 -> 0 | L82: =IF(E82=D82,IF('Parâmetros'!$C$10>=E82,G82,0),G82*MEDIAN(0,1,('Parâmetros'!$C$10-D82)/(E82-D82))) -> 0 | M82: =IF(ISNUMBER(SEARCH("GP",H82)),G82/(LEN(H82)-LEN(SUBSTITUTE(H82,"+",""))+1),0) -> 0 | N82: =IF(ISNUMBER(SEARCH("PM",H82)),G82/(LEN(H82)-LEN(SUBSTITUTE(H82,"+",""))+1),0) -> 0 | O82: =IF(ISNUMBER(SEARCH("Dev #1",H82)),G82/(LEN(H82)-LEN(SUBSTITUTE(H82,"+",""))+1),0) -> 20 | P82: =IF(ISNUMBER(SEARCH("Dev #2",H82)),G82/(LEN(H82)-LEN(SUBSTITUTE(H82,"+",""))+1),0) -> 0 | Q82: =IF(ISNUMBER(SEARCH("Dev #3",H82)),G82/(LEN(H82)-LEN(SUBSTITUTE(H82,"+",""))+1),0) -> 0 | R82: =IF(ISNUMBER(SEARCH("MKT",H82)),G82/(LEN(H82)-LEN(SUBSTITUTE(H82,"+",""))+1),0) -> 0 | S82: =(M82+N82)*'Parâmetros'!$C$15+(O82+P82+Q82+R82)*'Parâmetros'!$C$16 -> 500 | T82: =S82*I82 -> 0
A83: 98 | B83: 4.5 | C83: Elaborar FAQ e troubleshooting | D83: 46193 | E83: 46193 | F83: 2 | G83: 14 | H83: Dev #1+PM | I83: 0 | J83: =IF(I83>=1,"✅ Concluída",IF(I83>0,"🔵 Em execução",IF(E83<'Parâmetros'!$C$10,"🔴 Atrasada","⚪ Não iniciada"))) -> ⚪ Não iniciada | K83: =G83*I83 -> 0 | L83: =IF(E83=D83,IF('Parâmetros'!$C$10>=E83,G83,0),G83*MEDIAN(0,1,('Parâmetros'!$C$10-D83)/(E83-D83))) -> 0 | M83: =IF(ISNUMBER(SEARCH("GP",H83)),G83/(LEN(H83)-LEN(SUBSTITUTE(H83,"+",""))+1),0) -> 0 | N83: =IF(ISNUMBER(SEARCH("PM",H83)),G83/(LEN(H83)-LEN(SUBSTITUTE(H83,"+",""))+1),0) -> 7 | O83: =IF(ISNUMBER(SEARCH("Dev #1",H83)),G83/(LEN(H83)-LEN(SUBSTITUTE(H83,"+",""))+1),0) -> 7 | P83: =IF(ISNUMBER(SEARCH("Dev #2",H83)),G83/(LEN(H83)-LEN(SUBSTITUTE(H83,"+",""))+1),0) -> 0 | Q83: =IF(ISNUMBER(SEARCH("Dev #3",H83)),G83/(LEN(H83)-LEN(SUBSTITUTE(H83,"+",""))+1),0) -> 0 | R83: =IF(ISNUMBER(SEARCH("MKT",H83)),G83/(LEN(H83)-LEN(SUBSTITUTE(H83,"+",""))+1),0) -> 0 | S83: =(M83+N83)*'Parâmetros'!$C$15+(O83+P83+Q83+R83)*'Parâmetros'!$C$16 -> 385 | T83: =S83*I83 -> 0
A84: FASE 5 · Divulgação e Encerramento
A85: 101 | B85: 5.1 | C85: Desenvolver conteúdo e layout da landing page (RF25) | D85: 46196 | E85: 46196 | F85: 1 | G85: 8 | H85: Dev #1+MKT | I85: 0 | J85: =IF(I85>=1,"✅ Concluída",IF(I85>0,"🔵 Em execução",IF(E85<'Parâmetros'!$C$10,"🔴 Atrasada","⚪ Não iniciada"))) -> ⚪ Não iniciada | K85: =G85*I85 -> 0 | L85: =IF(E85=D85,IF('Parâmetros'!$C$10>=E85,G85,0),G85*MEDIAN(0,1,('Parâmetros'!$C$10-D85)/(E85-D85))) -> 0 | M85: =IF(ISNUMBER(SEARCH("GP",H85)),G85/(LEN(H85)-LEN(SUBSTITUTE(H85,"+",""))+1),0) -> 0 | N85: =IF(ISNUMBER(SEARCH("PM",H85)),G85/(LEN(H85)-LEN(SUBSTITUTE(H85,"+",""))+1),0) -> 0 | O85: =IF(ISNUMBER(SEARCH("Dev #1",H85)),G85/(LEN(H85)-LEN(SUBSTITUTE(H85,"+",""))+1),0) -> 4 | P85: =IF(ISNUMBER(SEARCH("Dev #2",H85)),G85/(LEN(H85)-LEN(SUBSTITUTE(H85,"+",""))+1),0) -> 0 | Q85: =IF(ISNUMBER(SEARCH("Dev #3",H85)),G85/(LEN(H85)-LEN(SUBSTITUTE(H85,"+",""))+1),0) -> 0 | R85: =IF(ISNUMBER(SEARCH("MKT",H85)),G85/(LEN(H85)-LEN(SUBSTITUTE(H85,"+",""))+1),0) -> 4 | S85: =(M85+N85)*'Parâmetros'!$C$15+(O85+P85+Q85+R85)*'Parâmetros'!$C$16 -> 200 | T85: =S85*I85 -> 0
A86: 102 | B86: 5.1 | C86: Publicar landing page e validar links | D86: 46197 | E86: 46197 | F86: 1 | G86: 8 | H86: Dev #1 | I86: 0 | J86: =IF(I86>=1,"✅ Concluída",IF(I86>0,"🔵 Em execução",IF(E86<'Parâmetros'!$C$10,"🔴 Atrasada","⚪ Não iniciada"))) -> ⚪ Não iniciada | K86: =G86*I86 -> 0 | L86: =IF(E86=D86,IF('Parâmetros'!$C$10>=E86,G86,0),G86*MEDIAN(0,1,('Parâmetros'!$C$10-D86)/(E86-D86))) -> 0 | M86: =IF(ISNUMBER(SEARCH("GP",H86)),G86/(LEN(H86)-LEN(SUBSTITUTE(H86,"+",""))+1),0) -> 0 | N86: =IF(ISNUMBER(SEARCH("PM",H86)),G86/(LEN(H86)-LEN(SUBSTITUTE(H86,"+",""))+1),0) -> 0 | O86: =IF(ISNUMBER(SEARCH("Dev #1",H86)),G86/(LEN(H86)-LEN(SUBSTITUTE(H86,"+",""))+1),0) -> 8 | P86: =IF(ISNUMBER(SEARCH("Dev #2",H86)),G86/(LEN(H86)-LEN(SUBSTITUTE(H86,"+",""))+1),0) -> 0 | Q86: =IF(ISNUMBER(SEARCH("Dev #3",H86)),G86/(LEN(H86)-LEN(SUBSTITUTE(H86,"+",""))+1),0) -> 0 | R86: =IF(ISNUMBER(SEARCH("MKT",H86)),G86/(LEN(H86)-LEN(SUBSTITUTE(H86,"+",""))+1),0) -> 0 | S86: =(M86+N86)*'Parâmetros'!$C$15+(O86+P86+Q86+R86)*'Parâmetros'!$C$16 -> 200 | T86: =S86*I86 -> 0
A87: 104 | B87: 5.2 | C87: Configurar repositório público c/ README e CONTRIBUTING | D87: 46197 | E87: 46197 | F87: 1 | G87: 8 | H87: Dev #1 | I87: 0 | J87: =IF(I87>=1,"✅ Concluída",IF(I87>0,"🔵 Em execução",IF(E87<'Parâmetros'!$C$10,"🔴 Atrasada","⚪ Não iniciada"))) -> ⚪ Não iniciada | K87: =G87*I87 -> 0 | L87: =IF(E87=D87,IF('Parâmetros'!$C$10>=E87,G87,0),G87*MEDIAN(0,1,('Parâmetros'!$C$10-D87)/(E87-D87))) -> 0 | M87: =IF(ISNUMBER(SEARCH("GP",H87)),G87/(LEN(H87)-LEN(SUBSTITUTE(H87,"+",""))+1),0) -> 0 | N87: =IF(ISNUMBER(SEARCH("PM",H87)),G87/(LEN(H87)-LEN(SUBSTITUTE(H87,"+",""))+1),0) -> 0 | O87: =IF(ISNUMBER(SEARCH("Dev #1",H87)),G87/(LEN(H87)-LEN(SUBSTITUTE(H87,"+",""))+1),0) -> 8 | P87: =IF(ISNUMBER(SEARCH("Dev #2",H87)),G87/(LEN(H87)-LEN(SUBSTITUTE(H87,"+",""))+1),0) -> 0 | Q87: =IF(ISNUMBER(SEARCH("Dev #3",H87)),G87/(LEN(H87)-LEN(SUBSTITUTE(H87,"+",""))+1),0) -> 0 | R87: =IF(ISNUMBER(SEARCH("MKT",H87)),G87/(LEN(H87)-LEN(SUBSTITUTE(H87,"+",""))+1),0) -> 0 | S87: =(M87+N87)*'Parâmetros'!$C$15+(O87+P87+Q87+R87)*'Parâmetros'!$C$16 -> 200 | T87: =S87*I87 -> 0
A88: 105 | B88: 5.2 | C88: Criar templates de issues e pull requests | D88: 46198 | E88: 46198 | F88: 1 | G88: 8 | H88: Dev #1 | I88: 0 | J88: =IF(I88>=1,"✅ Concluída",IF(I88>0,"🔵 Em execução",IF(E88<'Parâmetros'!$C$10,"🔴 Atrasada","⚪ Não iniciada"))) -> ⚪ Não iniciada | K88: =G88*I88 -> 0 | L88: =IF(E88=D88,IF('Parâmetros'!$C$10>=E88,G88,0),G88*MEDIAN(0,1,('Parâmetros'!$C$10-D88)/(E88-D88))) -> 0 | M88: =IF(ISNUMBER(SEARCH("GP",H88)),G88/(LEN(H88)-LEN(SUBSTITUTE(H88,"+",""))+1),0) -> 0 | N88: =IF(ISNUMBER(SEARCH("PM",H88)),G88/(LEN(H88)-LEN(SUBSTITUTE(H88,"+",""))+1),0) -> 0 | O88: =IF(ISNUMBER(SEARCH("Dev #1",H88)),G88/(LEN(H88)-LEN(SUBSTITUTE(H88,"+",""))+1),0) -> 8 | P88: =IF(ISNUMBER(SEARCH("Dev #2",H88)),G88/(LEN(H88)-LEN(SUBSTITUTE(H88,"+",""))+1),0) -> 0 | Q88: =IF(ISNUMBER(SEARCH("Dev #3",H88)),G88/(LEN(H88)-LEN(SUBSTITUTE(H88,"+",""))+1),0) -> 0 | R88: =IF(ISNUMBER(SEARCH("MKT",H88)),G88/(LEN(H88)-LEN(SUBSTITUTE(H88,"+",""))+1),0) -> 0 | S88: =(M88+N88)*'Parâmetros'!$C$15+(O88+P88+Q88+R88)*'Parâmetros'!$C$16 -> 200 | T88: =S88*I88 -> 0
A89: 107 | B89: 5.3 | C89: Definir plano de canais (dev.to, Product Hunt, redes) | D89: 46197 | E89: 46199 | F89: 4 | G89: 4 | H89: MKT | I89: 0 | J89: =IF(I89>=1,"✅ Concluída",IF(I89>0,"🔵 Em execução",IF(E89<'Parâmetros'!$C$10,"🔴 Atrasada","⚪ Não iniciada"))) -> ⚪ Não iniciada | K89: =G89*I89 -> 0 | L89: =IF(E89=D89,IF('Parâmetros'!$C$10>=E89,G89,0),G89*MEDIAN(0,1,('Parâmetros'!$C$10-D89)/(E89-D89))) -> 0 | M89: =IF(ISNUMBER(SEARCH("GP",H89)),G89/(LEN(H89)-LEN(SUBSTITUTE(H89,"+",""))+1),0) -> 0 | N89: =IF(ISNUMBER(SEARCH("PM",H89)),G89/(LEN(H89)-LEN(SUBSTITUTE(H89,"+",""))+1),0) -> 0 | O89: =IF(ISNUMBER(SEARCH("Dev #1",H89)),G89/(LEN(H89)-LEN(SUBSTITUTE(H89,"+",""))+1),0) -> 0 | P89: =IF(ISNUMBER(SEARCH("Dev #2",H89)),G89/(LEN(H89)-LEN(SUBSTITUTE(H89,"+",""))+1),0) -> 0 | Q89: =IF(ISNUMBER(SEARCH("Dev #3",H89)),G89/(LEN(H89)-LEN(SUBSTITUTE(H89,"+",""))+1),0) -> 0 | R89: =IF(ISNUMBER(SEARCH("MKT",H89)),G89/(LEN(H89)-LEN(SUBSTITUTE(H89,"+",""))+1),0) -> 4 | S89: =(M89+N89)*'Parâmetros'!$C$15+(O89+P89+Q89+R89)*'Parâmetros'!$C$16 -> 100 | T89: =S89*I89 -> 0
A90: 108 | B90: 5.3 | C90: Produzir conteúdo para divulgação | D90: 46202 | E90: 46204 | F90: 4 | G90: 4 | H90: MKT | I90: 0 | J90: =IF(I90>=1,"✅ Concluída",IF(I90>0,"🔵 Em execução",IF(E90<'Parâmetros'!$C$10,"🔴 Atrasada","⚪ Não iniciada"))) -> ⚪ Não iniciada | K90: =G90*I90 -> 0 | L90: =IF(E90=D90,IF('Parâmetros'!$C$10>=E90,G90,0),G90*MEDIAN(0,1,('Parâmetros'!$C$10-D90)/(E90-D90))) -> 0 | M90: =IF(ISNUMBER(SEARCH("GP",H90)),G90/(LEN(H90)-LEN(SUBSTITUTE(H90,"+",""))+1),0) -> 0 | N90: =IF(ISNUMBER(SEARCH("PM",H90)),G90/(LEN(H90)-LEN(SUBSTITUTE(H90,"+",""))+1),0) -> 0 | O90: =IF(ISNUMBER(SEARCH("Dev #1",H90)),G90/(LEN(H90)-LEN(SUBSTITUTE(H90,"+",""))+1),0) -> 0 | P90: =IF(ISNUMBER(SEARCH("Dev #2",H90)),G90/(LEN(H90)-LEN(SUBSTITUTE(H90,"+",""))+1),0) -> 0 | Q90: =IF(ISNUMBER(SEARCH("Dev #3",H90)),G90/(LEN(H90)-LEN(SUBSTITUTE(H90,"+",""))+1),0) -> 0 | R90: =IF(ISNUMBER(SEARCH("MKT",H90)),G90/(LEN(H90)-LEN(SUBSTITUTE(H90,"+",""))+1),0) -> 4 | S90: =(M90+N90)*'Parâmetros'!$C$15+(O90+P90+Q90+R90)*'Parâmetros'!$C$16 -> 100 | T90: =S90*I90 -> 0
A91: 109 | B91: 5.3 | C91: Redigir comunicado oficial de lançamento | D91: 46195 | E91: 46195 | F91: 1 | G91: 2 | H91: MKT+GP | I91: 0 | J91: =IF(I91>=1,"✅ Concluída",IF(I91>0,"🔵 Em execução",IF(E91<'Parâmetros'!$C$10,"🔴 Atrasada","⚪ Não iniciada"))) -> ⚪ Não iniciada | K91: =G91*I91 -> 0 | L91: =IF(E91=D91,IF('Parâmetros'!$C$10>=E91,G91,0),G91*MEDIAN(0,1,('Parâmetros'!$C$10-D91)/(E91-D91))) -> 0 | M91: =IF(ISNUMBER(SEARCH("GP",H91)),G91/(LEN(H91)-LEN(SUBSTITUTE(H91,"+",""))+1),0) -> 1 | N91: =IF(ISNUMBER(SEARCH("PM",H91)),G91/(LEN(H91)-LEN(SUBSTITUTE(H91,"+",""))+1),0) -> 0 | O91: =IF(ISNUMBER(SEARCH("Dev #1",H91)),G91/(LEN(H91)-LEN(SUBSTITUTE(H91,"+",""))+1),0) -> 0 | P91: =IF(ISNUMBER(SEARCH("Dev #2",H91)),G91/(LEN(H91)-LEN(SUBSTITUTE(H91,"+",""))+1),0) -> 0 | Q91: =IF(ISNUMBER(SEARCH("Dev #3",H91)),G91/(LEN(H91)-LEN(SUBSTITUTE(H91,"+",""))+1),0) -> 0 | R91: =IF(ISNUMBER(SEARCH("MKT",H91)),G91/(LEN(H91)-LEN(SUBSTITUTE(H91,"+",""))+1),0) -> 1 | S91: =(M91+N91)*'Parâmetros'!$C$15+(O91+P91+Q91+R91)*'Parâmetros'!$C$16 -> 55 | T91: =S91*I91 -> 0
A92: 111 | B92: 5.4 | C92: Executar deploy final e publicar versão npm | D92: 46195 | E92: 46195 | F92: 1 | G92: 4 | H92: Dev #1 | I92: 0 | J92: =IF(I92>=1,"✅ Concluída",IF(I92>0,"🔵 Em execução",IF(E92<'Parâmetros'!$C$10,"🔴 Atrasada","⚪ Não iniciada"))) -> ⚪ Não iniciada | K92: =G92*I92 -> 0 | L92: =IF(E92=D92,IF('Parâmetros'!$C$10>=E92,G92,0),G92*MEDIAN(0,1,('Parâmetros'!$C$10-D92)/(E92-D92))) -> 0 | M92: =IF(ISNUMBER(SEARCH("GP",H92)),G92/(LEN(H92)-LEN(SUBSTITUTE(H92,"+",""))+1),0) -> 0 | N92: =IF(ISNUMBER(SEARCH("PM",H92)),G92/(LEN(H92)-LEN(SUBSTITUTE(H92,"+",""))+1),0) -> 0 | O92: =IF(ISNUMBER(SEARCH("Dev #1",H92)),G92/(LEN(H92)-LEN(SUBSTITUTE(H92,"+",""))+1),0) -> 4 | P92: =IF(ISNUMBER(SEARCH("Dev #2",H92)),G92/(LEN(H92)-LEN(SUBSTITUTE(H92,"+",""))+1),0) -> 0 | Q92: =IF(ISNUMBER(SEARCH("Dev #3",H92)),G92/(LEN(H92)-LEN(SUBSTITUTE(H92,"+",""))+1),0) -> 0 | R92: =IF(ISNUMBER(SEARCH("MKT",H92)),G92/(LEN(H92)-LEN(SUBSTITUTE(H92,"+",""))+1),0) -> 0 | S92: =(M92+N92)*'Parâmetros'!$C$15+(O92+P92+Q92+R92)*'Parâmetros'!$C$16 -> 100 | T92: =S92*I92 -> 0
A93: 112 | B93: 5.4 | C93: Executar campanha de divulgação nos canais definidos | D93: 46196 | E93: 46198 | F93: 4 | G93: 4 | H93: MKT | I93: 0 | J93: =IF(I93>=1,"✅ Concluída",IF(I93>0,"🔵 Em execução",IF(E93<'Parâmetros'!$C$10,"🔴 Atrasada","⚪ Não iniciada"))) -> ⚪ Não iniciada | K93: =G93*I93 -> 0 | L93: =IF(E93=D93,IF('Parâmetros'!$C$10>=E93,G93,0),G93*MEDIAN(0,1,('Parâmetros'!$C$10-D93)/(E93-D93))) -> 0 | M93: =IF(ISNUMBER(SEARCH("GP",H93)),G93/(LEN(H93)-LEN(SUBSTITUTE(H93,"+",""))+1),0) -> 0 | N93: =IF(ISNUMBER(SEARCH("PM",H93)),G93/(LEN(H93)-LEN(SUBSTITUTE(H93,"+",""))+1),0) -> 0 | O93: =IF(ISNUMBER(SEARCH("Dev #1",H93)),G93/(LEN(H93)-LEN(SUBSTITUTE(H93,"+",""))+1),0) -> 0 | P93: =IF(ISNUMBER(SEARCH("Dev #2",H93)),G93/(LEN(H93)-LEN(SUBSTITUTE(H93,"+",""))+1),0) -> 0 | Q93: =IF(ISNUMBER(SEARCH("Dev #3",H93)),G93/(LEN(H93)-LEN(SUBSTITUTE(H93,"+",""))+1),0) -> 0 | R93: =IF(ISNUMBER(SEARCH("MKT",H93)),G93/(LEN(H93)-LEN(SUBSTITUTE(H93,"+",""))+1),0) -> 4 | S93: =(M93+N93)*'Parâmetros'!$C$15+(O93+P93+Q93+R93)*'Parâmetros'!$C$16 -> 100 | T93: =S93*I93 -> 0
A94: 113 | B94: 5.4 | C94: Ativar monitoramento via PostHog pós-lançamento | D94: 46196 | E94: 46196 | F94: 1 | G94: 8 | H94: Dev #2 | I94: 0 | J94: =IF(I94>=1,"✅ Concluída",IF(I94>0,"🔵 Em execução",IF(E94<'Parâmetros'!$C$10,"🔴 Atrasada","⚪ Não iniciada"))) -> ⚪ Não iniciada | K94: =G94*I94 -> 0 | L94: =IF(E94=D94,IF('Parâmetros'!$C$10>=E94,G94,0),G94*MEDIAN(0,1,('Parâmetros'!$C$10-D94)/(E94-D94))) -> 0 | M94: =IF(ISNUMBER(SEARCH("GP",H94)),G94/(LEN(H94)-LEN(SUBSTITUTE(H94,"+",""))+1),0) -> 0 | N94: =IF(ISNUMBER(SEARCH("PM",H94)),G94/(LEN(H94)-LEN(SUBSTITUTE(H94,"+",""))+1),0) -> 0 | O94: =IF(ISNUMBER(SEARCH("Dev #1",H94)),G94/(LEN(H94)-LEN(SUBSTITUTE(H94,"+",""))+1),0) -> 0 | P94: =IF(ISNUMBER(SEARCH("Dev #2",H94)),G94/(LEN(H94)-LEN(SUBSTITUTE(H94,"+",""))+1),0) -> 8 | Q94: =IF(ISNUMBER(SEARCH("Dev #3",H94)),G94/(LEN(H94)-LEN(SUBSTITUTE(H94,"+",""))+1),0) -> 0 | R94: =IF(ISNUMBER(SEARCH("MKT",H94)),G94/(LEN(H94)-LEN(SUBSTITUTE(H94,"+",""))+1),0) -> 0 | S94: =(M94+N94)*'Parâmetros'!$C$15+(O94+P94+Q94+R94)*'Parâmetros'!$C$16 -> 200 | T94: =S94*I94 -> 0
A95: 115 | B95: 5.5 | C95: Coletar feedback e métricas de adoção iniciais | D95: 46196 | E95: 46196 | F95: 2 | G95: 4 | H95: GP | I95: 0 | J95: =IF(I95>=1,"✅ Concluída",IF(I95>0,"🔵 Em execução",IF(E95<'Parâmetros'!$C$10,"🔴 Atrasada","⚪ Não iniciada"))) -> ⚪ Não iniciada | K95: =G95*I95 -> 0 | L95: =IF(E95=D95,IF('Parâmetros'!$C$10>=E95,G95,0),G95*MEDIAN(0,1,('Parâmetros'!$C$10-D95)/(E95-D95))) -> 0 | M95: =IF(ISNUMBER(SEARCH("GP",H95)),G95/(LEN(H95)-LEN(SUBSTITUTE(H95,"+",""))+1),0) -> 4 | N95: =IF(ISNUMBER(SEARCH("PM",H95)),G95/(LEN(H95)-LEN(SUBSTITUTE(H95,"+",""))+1),0) -> 0 | O95: =IF(ISNUMBER(SEARCH("Dev #1",H95)),G95/(LEN(H95)-LEN(SUBSTITUTE(H95,"+",""))+1),0) -> 0 | P95: =IF(ISNUMBER(SEARCH("Dev #2",H95)),G95/(LEN(H95)-LEN(SUBSTITUTE(H95,"+",""))+1),0) -> 0 | Q95: =IF(ISNUMBER(SEARCH("Dev #3",H95)),G95/(LEN(H95)-LEN(SUBSTITUTE(H95,"+",""))+1),0) -> 0 | R95: =IF(ISNUMBER(SEARCH("MKT",H95)),G95/(LEN(H95)-LEN(SUBSTITUTE(H95,"+",""))+1),0) -> 0 | S95: =(M95+N95)*'Parâmetros'!$C$15+(O95+P95+Q95+R95)*'Parâmetros'!$C$16 -> 120 | T95: =S95*I95 -> 0
A96: 116 | B96: 5.5 | C96: Apresentar relatório final à patrocinadora | D96: 46203 | E96: 46203 | F96: 1 | G96: 2 | H96: GP | I96: 0 | J96: =IF(I96>=1,"✅ Concluída",IF(I96>0,"🔵 Em execução",IF(E96<'Parâmetros'!$C$10,"🔴 Atrasada","⚪ Não iniciada"))) -> ⚪ Não iniciada | K96: =G96*I96 -> 0 | L96: =IF(E96=D96,IF('Parâmetros'!$C$10>=E96,G96,0),G96*MEDIAN(0,1,('Parâmetros'!$C$10-D96)/(E96-D96))) -> 0 | M96: =IF(ISNUMBER(SEARCH("GP",H96)),G96/(LEN(H96)-LEN(SUBSTITUTE(H96,"+",""))+1),0) -> 2 | N96: =IF(ISNUMBER(SEARCH("PM",H96)),G96/(LEN(H96)-LEN(SUBSTITUTE(H96,"+",""))+1),0) -> 0 | O96: =IF(ISNUMBER(SEARCH("Dev #1",H96)),G96/(LEN(H96)-LEN(SUBSTITUTE(H96,"+",""))+1),0) -> 0 | P96: =IF(ISNUMBER(SEARCH("Dev #2",H96)),G96/(LEN(H96)-LEN(SUBSTITUTE(H96,"+",""))+1),0) -> 0 | Q96: =IF(ISNUMBER(SEARCH("Dev #3",H96)),G96/(LEN(H96)-LEN(SUBSTITUTE(H96,"+",""))+1),0) -> 0 | R96: =IF(ISNUMBER(SEARCH("MKT",H96)),G96/(LEN(H96)-LEN(SUBSTITUTE(H96,"+",""))+1),0) -> 0 | S96: =(M96+N96)*'Parâmetros'!$C$15+(O96+P96+Q96+R96)*'Parâmetros'!$C$16 -> 60 | T96: =S96*I96 -> 0
A97: 117 | B97: 5.5 | C97: Obter aceite formal e encerrar o projeto | D97: 46204 | E97: 46204 | F97: 1 | G97: 2 | H97: PAT | I97: 0 | J97: =IF(I97>=1,"✅ Concluída",IF(I97>0,"🔵 Em execução",IF(E97<'Parâmetros'!$C$10,"🔴 Atrasada","⚪ Não iniciada"))) -> ⚪ Não iniciada | K97: =G97*I97 -> 0 | L97: =IF(E97=D97,IF('Parâmetros'!$C$10>=E97,G97,0),G97*MEDIAN(0,1,('Parâmetros'!$C$10-D97)/(E97-D97))) -> 0 | M97: =IF(ISNUMBER(SEARCH("GP",H97)),G97/(LEN(H97)-LEN(SUBSTITUTE(H97,"+",""))+1),0) -> 0 | N97: =IF(ISNUMBER(SEARCH("PM",H97)),G97/(LEN(H97)-LEN(SUBSTITUTE(H97,"+",""))+1),0) -> 0 | O97: =IF(ISNUMBER(SEARCH("Dev #1",H97)),G97/(LEN(H97)-LEN(SUBSTITUTE(H97,"+",""))+1),0) -> 0 | P97: =IF(ISNUMBER(SEARCH("Dev #2",H97)),G97/(LEN(H97)-LEN(SUBSTITUTE(H97,"+",""))+1),0) -> 0 | Q97: =IF(ISNUMBER(SEARCH("Dev #3",H97)),G97/(LEN(H97)-LEN(SUBSTITUTE(H97,"+",""))+1),0) -> 0 | R97: =IF(ISNUMBER(SEARCH("MKT",H97)),G97/(LEN(H97)-LEN(SUBSTITUTE(H97,"+",""))+1),0) -> 0 | S97: =(M97+N97)*'Parâmetros'!$C$15+(O97+P97+Q97+R97)*'Parâmetros'!$C$16 -> 0 | T97: =S97*I97 -> 0

Sheet Riscos
B2: ⚠ MATRIZ DE RISCOS — edite Prob. e Imp.; a Severidade e o Top-5 do Dashboard recalculam
B4: Cód. | C4: Descrição do Risco | D4: Categoria | E4: Prob. | F4: Imp. | G4: Sev. | H4: Nível | I4: Ação | J4: Responsável
B5: 1 | C5: Estimativas de prazo incorretas na fase de planejamento gerando atrasos no cronograma | D5: Gestão do projeto | E5: 3 | F5: 3 | G5: =E5*F5 -> 9 | H5: =IF(G5>=15,"🔴 Alto",IF(G5>=8,"🟡 Médio","🟢 Baixo")) -> 🟡 Médio | I5: Mitigar | J5: Gerente do Projeto | L5: =G5+(26-ROW()+5)/1000 -> 9.026
B6: 2 | C6: Mudanças no escopo não controladas | D6: Gestão do projeto | E6: 3 | F6: 4 | G6: =E6*F6 -> 12 | H6: =IF(G6>=15,"🔴 Alto",IF(G6>=8,"🟡 Médio","🟢 Baixo")) -> 🟡 Médio | I6: Mitigar | J6: Gerente do Projeto | L6: =G6+(26-ROW()+5)/1000 -> 12.025
B7: 3 | C7: Falha na comunicação entre os membros da equipe gerando retrabalho | D7: Gestão do projeto | E7: 3 | F7: 2 | G7: =E7*F7 -> 6 | H7: =IF(G7>=15,"🔴 Alto",IF(G7>=8,"🟡 Médio","🟢 Baixo")) -> 🟢 Baixo | I7: Mitigar | J7: Gerente do Projeto | L7: =G7+(26-ROW()+5)/1000 -> 6.024
B8: 4 | C8: Entregas não atenderem aos critérios de aceitação definidos no TAP | D8: Técnico | E8: 2 | F8: 4 | G8: =E8*F8 -> 8 | H8: =IF(G8>=15,"🔴 Alto",IF(G8>=8,"🟡 Médio","🟢 Baixo")) -> 🟡 Médio | I8: Mitigar | J8: Gerente do Projeto | L8: =G8+(26-ROW()+5)/1000 -> 8.023
B9: 5 | C9: Falta de revisão do plano de projeto | D9: Gestão do projeto | E9: 2 | F9: 3 | G9: =E9*F9 -> 6 | H9: =IF(G9>=15,"🔴 Alto",IF(G9>=8,"🟡 Médio","🟢 Baixo")) -> 🟢 Baixo | I9: Mitigar | J9: Gerente do Projeto | L9: =G9+(26-ROW()+5)/1000 -> 6.022
B10: 6 | C10: Disponibilidade limitada da equipe impactando o cronograma | D10: Organizacional | E10: 4 | F10: 3 | G10: =E10*F10 -> 12 | H10: =IF(G10>=15,"🔴 Alto",IF(G10>=8,"🟡 Médio","🟢 Baixo")) -> 🟡 Médio | I10: Aceitar | J10: Gerente do Projeto | L10: =G10+(26-ROW()+5)/1000 -> 12.021
B11: 7 | C11: Saída de um integrante da equipe durante o projeto | D11: Organizacional | E11: 5 | F11: 4 | G11: =E11*F11 -> 20 | H11: =IF(G11>=15,"🔴 Alto",IF(G11>=8,"🟡 Médio","🟢 Baixo")) -> 🔴 Alto | I11: Mitigar | J11: Gerente do Projeto | L11: =G11+(26-ROW()+5)/1000 -> 20.02
B12: 8 | C12: Dependência excessiva de um único integrante em partes críticas do projeto | D12: Organizacional | E12: 3 | F12: 3 | G12: =E12*F12 -> 9 | H12: =IF(G12>=15,"🔴 Alto",IF(G12>=8,"🟡 Médio","🟢 Baixo")) -> 🟡 Médio | I12: Mitigar | J12: Gerente do Projeto | L12: =G12+(26-ROW()+5)/1000 -> 9.019
B13: 9 | C13: Falta de alinhamento entre o gerente de projetos e o product manager nas decisões de escopo e prioridade | D13: Organizacional | E13: 2 | F13: 3 | G13: =E13*F13 -> 6 | H13: =IF(G13>=15,"🔴 Alto",IF(G13>=8,"🟡 Médio","🟢 Baixo")) -> 🟢 Baixo | I13: Mitigar | J13: Gerente do Projeto e Product Manager | L13: =G13+(26-ROW()+5)/1000 -> 6.018
B14: 10 | C14: Baixo engajamento ou feedback inadequado da patrocinadora durante o projeto | D14: Organizacional | E14: 2 | F14: 3 | G14: =E14*F14 -> 6 | H14: =IF(G14>=15,"🔴 Alto",IF(G14>=8,"🟡 Médio","🟢 Baixo")) -> 🟢 Baixo | I14: Mitigar | J14: Gerente do Projeto | L14: =G14+(26-ROW()+5)/1000 -> 6.017
B15: 11 | C15: Incompatibilidade entre os módulos durante a integração da ferramenta | D15: Técnico | E15: 3 | F15: 3 | G15: =E15*F15 -> 9 | H15: =IF(G15>=15,"🔴 Alto",IF(G15>=8,"🟡 Médio","🟢 Baixo")) -> 🟡 Médio | I15: Mitigar | J15: Desenvolvedores | L15: =G15+(26-ROW()+5)/1000 -> 9.016
B16: 12 | C16: Mudanças estruturais em frameworks suportados quebrando os templates gerados | D16: Técnico | E16: 4 | F16: 3 | G16: =E16*F16 -> 12 | H16: =IF(G16>=15,"🔴 Alto",IF(G16>=8,"🟡 Médio","🟢 Baixo")) -> 🟡 Médio | I16: Aceitar | J16: Desenvolvedores | L16: =G16+(26-ROW()+5)/1000 -> 12.015
... B30: 26 | C30: Critérios de aceite insuficientes para o novo perfil de usuário (MUD-02) | D30: Técnico | E30: 3 | F30: 4 | G30: =E30*F30 -> 12 | H30: =IF(G30>=15,"🔴 Alto",IF(G30>=8,"🟡 Médio","🟢 Baixo")) -> 🟡 Médio | I30: Mitigar | J30: Product Manager | L30: =G30+(26-ROW()+5)/1000 -> 12.001
C32: Severidade = Prob × Imp (1–5). Alto ≥15 · Médio 8–14 · Baixo ≤7. Fonte: PlanoDeRiscos_GP02.

Sheet Recursos e Custos
B2: 👥 ALOCAÇÃO DE RECURSOS — horas vêm do Cronograma (SUM por responsável)
B4: Cód. | C4: Integrante | D4: Função | E4: Limite TAP (h) | F4: Planejadas (h) | G4: % Util. | H4: Saldo (h) | I4: Status | J4: Observação
B5: GP | C5: Guilherme Marafon | D5: Gerente de Projetos | E5: 160 | F5: =SUM(Cronograma!$M$4:$M$97) -> 148.33333 | G5: =F5/E5 -> 0.92708333 | H5: =E5-F5 -> 11.666667 | I5: =IF(G5>=1,"🔴 ACIMA",IF(G5>=0.9,"🟡 LIMITE","🟢 OK")) -> 🟡 LIMITE
B6: PM | C6: Giulia Castelucci | D6: Product Manager | E6: 80 | F6: =SUM(Cronograma!$N$4:$N$97) -> 51 | G6: =F6/E6 -> 0.6375 | H6: =E6-F6 -> 29 | I6: =IF(G6>=1,"🔴 ACIMA",IF(G6>=0.9,"🟡 LIMITE","🟢 OK")) -> 🟢 OK
B7: Dev #1 | C7: Vinícius Trevisan | D7: Desenvolvedor | E7: 330 | F7: =SUM(Cronograma!$O$4:$O$97) -> 342.33333 | G7: =F7/E7 -> 1.0373737 | H7: =E7-F7 -> -12.333333 | I7: =IF(G7>=1,"🔴 ACIMA",IF(G7>=0.9,"🟡 LIMITE","🟢 OK")) -> 🔴 ACIMA
B8: Dev #2 | C8: Guilherme Reis | D8: Desenvolvedor | E8: 330 | F8: =SUM(Cronograma!$P$4:$P$97) -> 291.33333 | G8: =F8/E8 -> 0.88282828 | H8: =E8-F8 -> 38.666667 | I8: =IF(G8>=1,"🔴 ACIMA",IF(G8>=0.9,"🟡 LIMITE","🟢 OK")) -> 🟢 OK
B9: Dev #3 | C9: Amanda Freire | D9: Desenvolvedor | E9: 330 | F9: =SUM(Cronograma!$Q$4:$Q$97) -> 136 | G9: =F9/E9 -> 0.41212121 | H9: =E9-F9 -> 194 | I9: =IF(G9>=1,"🔴 ACIMA",IF(G9>=0.9,"🟡 LIMITE","🟢 OK")) -> 🟢 OK | J9: DESLIGADA — tarefas remanescentes redistribuídas
B10: MKT | C10: Valentina Lago | D10: Marketing | E10: 20 | F10: =SUM(Cronograma!$R$4:$R$97) -> 17 | G10: =F10/E10 -> 0.85 | H10: =E10-F10 -> 3 | I10: =IF(G10>=1,"🔴 ACIMA",IF(G10>=0.9,"🟡 LIMITE","🟢 OK")) -> 🟢 OK
B12: 💰 CUSTOS — Custo Planejado = horas (cronograma) × rate
B14: Cód. | C14: Integrante | D14: Horas Planej. | E14: R$/h | F14: Custo Planejado | G14: Custo TAP | H14: Diferença
B15: GP | C15: Guilherme Marafon | D15: =F5 -> 148.33333 | E15: ='Parâmetros'!$C$15 -> 30 | F15: =D15*E15 -> 4450 | G15: 4800 | H15: =F15-G15 -> -350
B16: PM | C16: Giulia Castelucci | D16: =F6 -> 51 | E16: ='Parâmetros'!$C$15 -> 30 | F16: =D16*E16 -> 1530 | G16: 2400 | H16: =F16-G16 -> -870
B17: Dev #1 | C17: Vinícius Trevisan | D17: =F7 -> 342.33333 | E17: ='Parâmetros'!$C$16 -> 25 | F17: =D17*E17 -> 8558.3333 | G17: 8250 | H17: =F17-G17 -> 308.33333
B18: Dev #2 | C18: Guilherme Reis | D18: =F8 -> 291.33333 | E18: ='Parâmetros'!$C$16 -> 25 | F18: =D18*E18 -> 7283.3333 | G18: 8250 | H18: =F18-G18 -> -966.66667
B19: Dev #3 | C19: Amanda Freire | D19: =F9 -> 136 | E19: ='Parâmetros'!$C$16 -> 25 | F19: =D19*E19 -> 3400 | G19: 8250 | H19: =F19-G19 -> -4850
B20: MKT | C20: Valentina Lago | D20: =F10 -> 17 | E20: ='Parâmetros'!$C$16 -> 25 | F20: =D20*E20 -> 425 | G20: 500 | H20: =F20-G20 -> -75
C21: TOTAL | D21: =SUM(D15:D20) -> 986 | F21: =SUM(F15:F20) -> 25646.667 | G21: =SUM(G15:G20) -> 32450 | H21: =SUM(H15:H20) -> -6803.3333
B22: Diferença = Custo Planejado − Custo TAP. Vermelho = estoura o teto · Verde = sobra (folga).
B23: 💸 CUSTO POR FASE (calculado do cronograma)
B25: Fase | D25: Custo (R$) | E25: % do Total
B26: F1 · Gerenciamento | D26: =SUM(Cronograma!$S$4:$S$21) -> 2700 | E26: =D26/D31 -> 0.10527684
B27: F2 · Definição & Design | D27: =SUM(Cronograma!$S$23:$S$41) -> 2990 | E27: =D27/D31 -> 0.11658435
B28: F3 · Implementação | D28: =SUM(Cronograma!$S$43:$S$69) -> 12920 | E28: =D28/D31 -> 0.50376917
B29: F4 · Testes & Doc. | D29: =SUM(Cronograma!$S$71:$S$83) -> 5401.6667 | E29: =D29/D31 -> 0.21061866
B30: F5 · Divulgação & Encerr. | D30: =SUM(Cronograma!$S$85:$S$97) -> 1635 | E30: =D30/D31 -> 0.063750975
B31: TOTAL | D31: =SUM(D26:D30) -> 25646.667 | E31: 1
B33: Obs.: custo = horas alocadas no cronograma × rate (Parâmetros). Infra (Gemini, PostHog, Supabase, npm, Vercel) em planos gratuitos — R$ 0.

Sheet Parâmetros
B2: ⚙ PARÂMETROS & PREMISSAS — KYBERNUS CLI
E3: 💡 Identificação fixa + premissas de cálculo. A Data de Status controla o Avanço Planejado (curva do cronograma). O BAC é o orçamento aprovado. O AC (custo real) e as rates são editáveis. O Avanço Real vem do % Real lançado tarefa a tarefa na aba Cronograma — não se edita aqui.
B4: IDENTIFICAÇÃO
B5: Nome do Projeto | C5: Kybernus CLI
B6: Gerente do Projeto | C6: Guilherme Marafon
B7: Patrocinadora | C7: Prof. Rosilene
B8: Data de Início | C8: 46085
B9: Data de Término Planejada | C9: 46204
B10: Data de Status (Reporte) | C10: 46173
B12: PREMISSAS DE CUSTO (EDITÁVEL)
B13: Orçamento Aprovado — BAC (R$) | C13: 35695
B14: Custo Real Acumulado — AC (R$) [calc.] | C14: =SUM(Cronograma!$T$4:$T$97) -> 11290
B15: Rate GP / PM (R$/h) | C15: 30
B16: Rate Dev / MKT (R$/h) | C16: 25
B18: INDICADORES CALCULADOS
B19: Total de Horas (cronograma) | C19: =SUM(Cronograma!$G$4:$G$97) -> 1007
B20: Total de Atividades | C20: =COUNT(Cronograma!$G$4:$G$97) -> 90
B21: Avanço Real (% Real lançado) | C21: =SUM(Cronograma!$K$4:$K$97)/SUM(Cronograma!$G$4:$G$97) -> 0.43177756
B22: Avanço Planejado (data de status) | C22: =SUM(Cronograma!$L$4:$L$97)/SUM(Cronograma!$G$4:$G$97) -> 0.64392885

Sheet Controle_Status
B2: 📋 PAINEL DE CENÁRIO ATUAL
E3: Resumo do cenário reportado na data de status. O avanço real (40%) é apurado pelo % Real lançado tarefa a tarefa no Cronograma. O avanço planejado (~62%) vem da curva do cronograma na data de status. A diferença explica o status 🔴.
B4: INDICADORES-CHAVE
B5: Avanço Real (apurado) | C5: ='Parâmetros'!$C$21 -> 0.43177756
B6: Avanço Planejado (cronograma) | C6: ='Parâmetros'!$C$22 -> 0.64392885
B7: Defasagem de prazo | C7: ='Parâmetros'!$C$21-'Parâmetros'!$C$22 -> -0.2121513
B8: Carga adicional aprovada (escopo) | C8: +39 h
B9: Origem da mudança | C9: Novo perfil de acesso, permissões e segurança
B10: Mudança aprovada pelo patrocinador | C10: Sim
B11: Desenvolvedor desligado | C11: Amanda Freire (Dev #3)
B12: Tratativa do desligamento | C12: Tarefas remanescentes redistribuídas a Dev #1 e Dev #2

Sheet Marcos
B2: 🎯 MARCOS DO PROJETO
B4: ID | C4: Marco | D4: Data Prevista | E4: Situação
B5: M0 | C5: Gerenciamento do Projeto | D5: 46092 | E5: =IF(D5<='Parâmetros'!$C$10,"Concluído","Previsto") -> Concluído
B6: M1 | C6: Definição e Design | D6: 46113 | E6: =IF(D6<='Parâmetros'!$C$10,"Concluído","Previsto") -> Concluído
B7: M2 | C7: Implementação das Funcionalidades | D7: 46176 | E7: =IF(D7<='Parâmetros'!$C$10,"Concluído","Previsto") -> Previsto
B8: M3 | C8: Testes e Documentação | D8: 46190 | E8: =IF(D8<='Parâmetros'!$C$10,"Concluído","Previsto") -> Previsto
B9: M4 | C9: Divulgação e Encerramento | D9: 46204 | E9: =IF(D9<='Parâmetros'!$C$10,"Concluído","Previsto") -> Previsto

Sheet Partes Interessadas
B2: 🤝 PARTES INTERESSADAS — Engajamento
B4: Parte Interessada | C4: Engajamento | D4: Impacto | E4: Estratégia
B5: Patrocinadora (Prof. Rosilene) | C5: A → L | D5: Alto | E5: Reuniões periódicas de prestação de contas com entregas e critérios de aceite claros; envolvê-la nas decisões de escopo.
B6: Gerente de Projeto (G. Marafon) | C6: L → L | D6: Alto | E6: Autonomia para decisões operacionais e acesso a informações em tempo real via ClickUp.
B7: Product Manager (G. Castelucci) | C7: A → L | D7: Alto | E7: Envolver nas decisões de priorização de requisitos e validação de escopo; reconhecer contribuições.
B8: Desenvolvedores (#1,#2,#3) | C8: A → L | D8: Alto | E8: Clareza nas tarefas e autonomia técnica; reconhecer contribuições e evitar sobrecarga além do TAP.
B9: Consultor de Marketing (V. Lago) | C9: N → A | D9: Médio | E9: Mostrar impacto estratégico do lançamento; envolver no posicionamento desde a Fase 4.
B10: Tech Leads / Arquitetos | C10: D → A | D10: Médio | E10: Compartilhar documentação técnica e padrões (MVC, Clean, Hexagonal); convidar para testes externos.
B11: Desenvolvedores (usuários finais) | C11: D → A | D11: Alto | E11: Landing page clara com instruções; garantir meta de 80% de sucesso sem suporte.
B12: Comunidade Open-Source | C12: D → A | D12: Médio | E12: Repositório modelo no GitHub (README, CONTRIBUTING, templates); divulgar no dev.to e Product Hunt.
B13: Empresas de Tecnologia | C13: D → N | D13: Baixo | E13: Monitorar interesse via telemetria após o lançamento; sem ação direta no ciclo atual.
B15: Legenda: A=Apoiador · N=Neutro · R=Resistente · D=Desinformado · L=Lidera (atual → desejado)

Sheet Dados
A1: TABELAS DE APOIO (recalculadas automaticamente — não editar)
A3: Fase | B3: Horas Totais | C3: Horas Realizadas (EV) | D3: % Concl.
A4: F1 · Gerenciamento | B4: =SUM(Cronograma!$G$4:$G$21) -> 94 | C4: =SUM(Cronograma!$K$4:$K$21) -> 58 | D4: =IF(B4=0,0,C4/B4) -> 0.61702128
A5: F2 · Definição & Design | B5: =SUM(Cronograma!$G$23:$G$41) -> 112 | C5: =SUM(Cronograma!$K$23:$K$41) -> 112 | D5: =IF(B5=0,0,C5/B5) -> 1
A6: F3 · Implementação | B6: =SUM(Cronograma!$G$43:$G$69) -> 529 | C6: =SUM(Cronograma!$K$43:$K$69) -> 264.8 | D6: =IF(B6=0,0,C6/B6) -> 0.50056711
A7: F4 · Testes & Doc. | B7: =SUM(Cronograma!$G$71:$G$83) -> 206 | C7: =SUM(Cronograma!$K$71:$K$83) -> 0 | D7: =IF(B7=0,0,C7/B7) -> 0
A8: F5 · Divulgação & Encerr. | B8: =SUM(Cronograma!$G$85:$G$97) -> 66 | C8: =SUM(Cronograma!$K$85:$K$97) -> 0 | D8: =IF(B8=0,0,C8/B8) -> 0
A10: Mês | B10: Acum. Planejado (h) | C10: Acum. Realizado (h)
A11: Mar/26 | B11: =SUMPRODUCT((Cronograma!$E$4:$E$97<=DATE(2026,3,31))*Cronograma!$G$4:$G$97) -> 70 | C11: =B11*('Parâmetros'!$C$21/'Parâmetros'!$C$22) -> 46.937529
A12: Abr/26 | B12: =SUMPRODUCT((Cronograma!$E$4:$E$97<=DATE(2026,4,30))*Cronograma!$G$4:$G$97) -> 230 | C12: =B12*('Parâmetros'!$C$21/'Parâmetros'!$C$22) -> 154.22331
A13: Mai/26 | B13: =SUMPRODUCT((Cronograma!$E$4:$E$97<=DATE(2026,5,31))*Cronograma!$G$4:$G$97) -> 632 | C13: =B13*('Parâmetros'!$C$21/'Parâmetros'!$C$22) -> 423.77883
A14: Jun/26 | B14: =SUMPRODUCT((Cronograma!$E$4:$E$97<=DATE(2026,6,30))*Cronograma!$G$4:$G$97) -> 979
A15: Jul/26 | B15: =SUMPRODUCT((Cronograma!$E$4:$E$97<=DATE(2026,7,31))*Cronograma!$G$4:$G$97) -> 1007
A17: Recurso | B17: % Utilização | C17: Planejadas (h) | D17: Limite (h)
A18: GP | B18: =C18/D18 -> 0.92708333 | C18: ='Recursos e Custos'!$F$5 -> 148.33333 | D18: 160
A19: PM | B19: =C19/D19 -> 0.6375 | C19: ='Recursos e Custos'!$F$6 -> 51 | D19: 80
A20: Dev #1 | B20: =C20/D20 -> 1.0373737 | C20: ='Recursos e Custos'!$F$7 -> 342.33333 | D20: 330
A21: Dev #2 | B21: =C21/D21 -> 0.88282828 | C21: ='Recursos e Custos'!$F$8 -> 291.33333 | D21: 330
A22: Dev #3 | B22: =C22/D22 -> 0.41212121 | C22: ='Recursos e Custos'!$F$9 -> 136 | D22: 330
A23: MKT | B23: =C23/D23 -> 0.85 | C23: ='Recursos e Custos'!$F$10 -> 17 | D23: 20
A25: Categoria | B25: Severidade (Σ)
A26: Técnico | B26: =SUMIF(Riscos!$D$5:$D$30,A26,Riscos!$G$5:$G$30) -> 69
A27: Organizacional | B27: =SUMIF(Riscos!$D$5:$D$30,A27,Riscos!$G$5:$G$30) -> 80
A28: Gestão do projeto | B28: =SUMIF(Riscos!$D$5:$D$30,A28,Riscos!$G$5:$G$30) -> 58
A29: Externo | B29: =SUMIF(Riscos!$D$5:$D$30,A29,Riscos!$G$5:$G$30) -> 13
A30: Aquisições | B30: =SUMIF(Riscos!$D$5:$D$30,A30,Riscos!$G$5:$G$30) -> 6
A32: Fase | B32: Previsto (PV h) | C32: Realizado (EV h)
A33: F1 · Gerenciamento | B33: =SUM(Cronograma!$L$4:$L$21) -> 74.436356 | C33: =SUM(Cronograma!$K$4:$K$21) -> 58
A34: F2 · Definição & Design | B34: =SUM(Cronograma!$L$23:$L$41) -> 112 | C34: =SUM(Cronograma!$K$23:$K$41) -> 112
A35: F3 · Implementação | B35: =SUM(Cronograma!$L$43:$L$69) -> 462 | C35: =SUM(Cronograma!$K$43:$K$69) -> 264.8
A36: F4 · Testes & Doc. | B36: =SUM(Cronograma!$L$71:$L$83) -> 0 | C36: =SUM(Cronograma!$K$71:$K$83) -> 0
A37: F5 · Divulgação & Encerr. | B37: =SUM(Cronograma!$L$85:$L$97) -> 0 | C37: =SUM(Cronograma!$K$85:$K$97) -> 0
A39: EVM (auto)
A40: SPI | B40: =IF('Parâmetros'!$C$22=0,0,'Parâmetros'!$C$21/'Parâmetros'!$C$22) -> 0.67053612
A41: EV | B41: ='Parâmetros'!$C$21*'Parâmetros'!$C$13 -> 15412.3
A42: CPI | B42: =IF('Parâmetros'!$C$14=0,0,('Parâmetros'!$C$21*'Parâmetros'!$C$13)/'Parâmetros'!$C$14) -> 1.3651284
A43: PV | B43: ='Parâmetros'!$C$22*'Parâmetros'!$C$13 -> 22985.04
A44: CV | B44: =('Parâmetros'!$C$21*'Parâmetros'!$C$13)-'Parâmetros'!$C$14 -> 4122.2999
A45: SV | B45: =('Parâmetros'!$C$21*'Parâmetros'!$C$13)-('Parâmetros'!$C$22*'Parâmetros'!$C$13) -> -7572.7405
A46: %ORC | B46: ='Parâmetros'!$C$14/'Parâmetros'!$C$13 -> 0.3162908
A48: TOP-5 RISCOS (dinâmico)
A49: # | B49: Cód | C49: Descrição | D49: Sev | E49: Nível
A50: 1 | B50: {=INDEX(Riscos!$B$5:$B$30,MATCH(LARGE(Riscos!$L$5:$L$30,1),Riscos!$L$5:$L$30,0))} -> 7 | C50: {=INDEX(Riscos!$C$5:$C$30,MATCH(LARGE(Riscos!$L$5:$L$30,1),Riscos!$L$5:$L$30,0))} -> Saída de um integrante da equipe durante o projeto | D50: {=INDEX(Riscos!$G$5:$G$30,MATCH(LARGE(Riscos!$L$5:$L$30,1),Riscos!$L$5:$L$30,0))} -> 20 | E50: {=INDEX(Riscos!$H$5:$H$30,MATCH(LARGE(Riscos!$L$5:$L$30,1),Riscos!$L$5:$L$30,0))} -> 🔴 Alto
A51: 2 | B51: {=INDEX(Riscos!$B$5:$B$30,MATCH(LARGE(Riscos!$L$5:$L$30,2),Riscos!$L$5:$L$30,0))} -> 22 | C51: {=INDEX(Riscos!$C$5:$C$30,MATCH(LARGE(Riscos!$L$5:$L$30,2),Riscos!$L$5:$L$30,0))} -> Atraso no prazo final 01/07 devido à defasagem e redistribuição (MUD-01) | D51: {=INDEX(Riscos!$G$5:$G$30,MATCH(LARGE(Riscos!$L$5:$L$30,2),Riscos!$L$5:$L$30,0))} -> 16 | E51: {=INDEX(Riscos!$H$5:$H$30,MATCH(LARGE(Riscos!$L$5:$L$30,2),Riscos!$L$5:$L$30,0))} -> 🔴 Alto
A52: 3 | B52: {=INDEX(Riscos!$B$5:$B$30,MATCH(LARGE(Riscos!$L$5:$L$30,3),Riscos!$L$5:$L$30,0))} -> 2 | C52: {=INDEX(Riscos!$C$5:$C$30,MATCH(LARGE(Riscos!$L$5:$L$30,3),Riscos!$L$5:$L$30,0))} -> Mudanças no escopo não controladas | D52: {=INDEX(Riscos!$G$5:$G$30,MATCH(LARGE(Riscos!$L$5:$L$30,3),Riscos!$L$5:$L$30,0))} -> 12 | E52: {=INDEX(Riscos!$H$5:$H$30,MATCH(LARGE(Riscos!$L$5:$L$30,3),Riscos!$L$5:$L$30,0))} -> 🟡 Médio
A53: 4 | B53: {=INDEX(Riscos!$B$5:$B$30,MATCH(LARGE(Riscos!$L$5:$L$30,4),Riscos!$L$5:$L$30,0))} -> 6 | C53: {=INDEX(Riscos!$C$5:$C$30,MATCH(LARGE(Riscos!$L$5:$L$30,4),Riscos!$L$5:$L$30,0))} -> Disponibilidade limitada da equipe impactando o cronograma | D53: {=INDEX(Riscos!$G$5:$G$30,MATCH(LARGE(Riscos!$L$5:$L$30,4),Riscos!$L$5:$L$30,0))} -> 12 | E53: {=INDEX(Riscos!$H$5:$H$30,MATCH(LARGE(Riscos!$L$5:$L$30,4),Riscos!$L$5:$L$30,0))} -> 🟡 Médio
A54: 5 | B54: {=INDEX(Riscos!$B$5:$B$30,MATCH(LARGE(Riscos!$L$5:$L$30,5),Riscos!$L$5:$L$30,0))} -> 12 | C54: {=INDEX(Riscos!$C$5:$C$30,MATCH(LARGE(Riscos!$L$5:$L$30,5),Riscos!$L$5:$L$30,0))} -> Mudanças estruturais em frameworks suportados quebrando os templates gerados | D54: {=INDEX(Riscos!$G$5:$G$30,MATCH(LARGE(Riscos!$L$5:$L$30,5),Riscos!$L$5:$L$30,0))} -> 12 | E54: {=INDEX(Riscos!$H$5:$H$30,MATCH(LARGE(Riscos!$L$5:$L$30,5),Riscos!$L$5:$L$30,0))} -> 🟡 Médio
